Workbook

Sheet Invoice
X2: crt + h
J3: 52, RAJASWA COLONY,TANKI PATH FREEGANJ, UJJAIN MP | X3: Crt + u
J4: PH 0734-2530547,9425332517 | X4: crt + L
J5: SEED LIC NO- 1178
B6: नाम | G6: Name | K6: Invoice no | L6: =MAXIFS(Sale!B:B,Sale!A:A,A10)+1 -> 6
B7: ग्राम | G7: Village | K7: Date | L7: 13-09-2025
B8: मोबाईल | G8: Phone no | K8: GST EXEMPTED WHEAT SEED
B9: Sno | C9: Invoice no | D9: Customer name | E9: Village | F9: Mobile No | G9: remark | H9: Particular | I9: Bags | J9: Packing | K9: Quantity | L9: Rate | M9: Amount | N9: TOTAL BILL AMOUT | O9: Discoumt | P9: GRAND TOTAL | Q9: Advance | R9: Card Pay | S9: CASH TAKEN | T9: Difference | U9: Remark | V9: date | W9: BAG STOCK | X9: QTL STOCK
A10: =K$19 -> #N/A | B10: 1 | C10: =L$6 -> 6 | D10: =H$6 | E10: =H$7 | F10: =H$8 | G10: =L17 | J10: =if(H10>0,40,"") | K10: =IFERROR(I10*J10/100,"") -> 0 | L10: =iferror(VLOOKUP(H10,Table2[[Variety]:[RATE]],5,false),"") | M10: =iferror(L10*K10, "") -> 0 | N10: =M18 -> 0 | O10: =M19 | P10: =M20 -> 0 | Q10: =M21 | R10: =M22 | S10: =M23 -> 0 | T10: =M24 -> 0 | U10: =K18 -> VS | V10: =L$7 -> 13-09-2025 | W10: =VLOOKUP(H10,Table2[[Variety]:[In Stock]],4,false)-I10 -> #N/A | X10: =W10/0.4 -> #N/A
A11: =K$19 -> #N/A | B11: 2 | C11: =L$6 -> 6 | D11: =H$6 | E11: =H$7 | F11: =H$8 | J11: =if(H11>0,40,"") | K11: =IFERROR(I11*J11/100,"") -> 0 | L11: =iferror(VLOOKUP(H11,Table2[[Variety]:[RATE]],5,false),"") | M11: =iferror(L11*K11, "") -> 0 | V11: =L$7 -> 13-09-2025 | W11: =VLOOKUP(H11,Table2[[Variety]:[In Stock]],4,false)-I11 -> #N/A | X11: =W11/0.4 -> #N/A
A12: =K$19 -> #N/A | B12: 3 | C12: =L$6 -> 6 | D12: =H$6 | E12: =H$7 | F12: =H$8 | J12: =if(H12>0,40,"") | K12: =IFERROR(I12*J12/100,"") -> 0 | L12: =iferror(VLOOKUP(H12,Table2[[Variety]:[RATE]],5,false),"") | M12: =iferror(L12*K12, "") -> 0 | V12: =L$7 -> 13-09-2025 | W12: =VLOOKUP(H12,Table2[[Variety]:[In Stock]],4,false)-I12 -> #N/A | X12: =W12/0.4 -> #N/A
A13: =K$19 -> #N/A | B13: 4 | C13: =L$6 -> 6 | D13: =H$6 | E13: =H$7 | F13: =H$8 | J13: =if(H13>0,40,"") | K13: =IFERROR(I13*J13/100,"") -> 0 | L13: =iferror(VLOOKUP(H13,Table2[[Variety]:[RATE]],5,false),"") | M13: =iferror(L13*K13, "") -> 0 | V13: =L$7 -> 13-09-2025 | W13: =VLOOKUP(H13,Table2[[Variety]:[In Stock]],4,false)-I13 -> #N/A | X13: =W13/0.4 -> #N/A
A14: =K$19 -> #N/A | B14: 5 | C14: =L$6 -> 6 | D14: =H$6 | E14: =H$7 | F14: =H$8 | J14: =if(H14>0,40,"") | K14: =IFERROR(I14*J14/100,"") -> 0 | L14: =iferror(VLOOKUP(H14,Table2[[Variety]:[RATE]],5,false),"") | M14: =iferror(L14*K14, "") -> 0 | V14: =L$7 -> 13-09-2025 | W14: =VLOOKUP(H14,Table2[[Variety]:[In Stock]],4,false)-I14 -> #N/A | X14: =W14/0.4 -> #N/A
H15: . | I15: =sum(I10:I14) -> 0 | K15: =sum(K10:K14) -> 0 | L15: =sum(M10:M14) -> 0 | W15: Diff | X15: 0 | Y15: ="https://vasundharaseeds.in/pay.html?amount=" & sum(M10:M14) & "&invoice=" & MAXIFS(Sale!B:B,Sale!A:A,A10)+1 -> https://vasundharaseeds.in/pay.html?amount=0&invoice=6
H17: . | K17: Remark- | X17: =sum(Y18:Y24) -> 0
H18: . | K18: =IF(M36=0,IF(M34>0,"BANK-VS","VS"),"Credit-vs") -> VS | L18: Total | M18: =L15 -> 0 | Y18: =W18*X18 -> 0
H19: . | K19: =VLOOKUP(H10,Table2[],10,false) -> #N/A | Y19: =W19*X19 -> 0
H20: . | L20: Bill amount | M20: =M18-M19 -> 0 | Y20: =W20*X20 -> 0
H21: . | L21: Advance | Y21: =W21*X21 -> 0
H22: . | L22: Account Pay | Y22: =W22*X22 -> 0
H23: . | L23: Cash Taken | M23: =X17 -> 0 | Y23: =W23*X23 -> 0
H24: कृषक के हस्ताक्षर | J24: वास्ते वसुंधरा सीड्स | L24: Difference | M24: =M20-M21-M22-M23 -> 0 | Y24: =W24*X24 -> 0
C25: .
C26: .
C27: HI-8777 PUSA GEHU APR-2024-12-763-135627-FI-(I) | D27: VS | F27: I)
C28: GW-513 APR-2024-12-763-135624-FII-(I)-A | D28: VS | F28: -A
C29: GW-513 APR-2024-12-763-135624-FII-(I)-B | D29: VS | F29: -B
C30: GW-513 APR-2024-12-763-135624-FII-(II) | D30: VS | F30: I)
C31: HI-1544 (पूर्णा) APR-2024-12-763-135662-FI | D31: VS | F31: FI
C32: C-306 APR-2024-12-763-135670-FI | D32: VS | F32: FI
C33: HI-8830 (पूसा किर्ति) APR-2024-12-763-135635-FI-A | D33: VS | F33: -A
C34: HI-8830 (पूसा किर्ति) APR-2024-12-763-135635-FI-B | D34: VS | F34: -B
C35: HI-8663 (पोषण ) APR-2024-12-763-135628-FI-B | D35: VS | F35: -B
C36: LOK-1 APR-2024-12-763-135669-FI-A | D36: VS | F36: -A
C37: LOK-1 APR-2024-12-763-135668-FI-A | D37: VS | F37: -A
C38: LOK-1 APR-2024-12-763-135667-FI-A | D38: VS | F38: -A
... C52: HI-8830 (पूसा किर्ति) 40 KG | D52: TL | F52: KG
C53: GW-513 40 KG | D53: TL | F53: KG | H53: `
J55: 52, RAJASWA COLONY,TANKI PATH FREEGANJ, UJJAIN MP
J56: PH 0734-2530547,9425332517
J57: SEED LIC NO- 1178
B58: नाम | G58: Name | H58: DINESH RAGHUWANSHI | K58: Invoice no | L58: 19273
B59: ग्राम | G59: Village | H59: KAKARAYI | K59: Date | L59: 13-09-2025
B60: मोबाईल | G60: Phone no | H60: 9977096885 | K60: GST EXEMPTED WHEAT SEED
B61: Sno | C61: Invoice no | D61: Customer name | E61: Village | F61: Mobile No | G61: remark | H61: Particular | I61: Bags | J61: Packing | K61: Quantity | L61: Rate | M61: Amount
B62: 1 | C62: 19273 | D62: DINESH RAGHUWANSHI | E62: KAKARAYI | F62: 9977096885 | H62: HI-1650(पूसा ओजस्वी) MAR-25-12-763-40(3) (FII) | I62: 10 | J62: 40 | K62: 4 | L62: 5500 | M62: 22000
B63: 2 | C63: 19273 | D63: DINESH RAGHUWANSHI | E63: KAKARAYI | F63: 9977096885 | H63: GW-513 MAR-25-12-763-20(2) (CI) | I63: 2 | J63: 40 | K63: 0.8 | L63: 5500 | M63: 4400
B64: 3 | C64: 19273 | D64: DINESH RAGHUWANSHI | E64: KAKARAYI | F64: 9977096885 | K64: 0 | M64: 0
B65: 4 | C65: 19273 | D65: DINESH RAGHUWANSHI | E65: KAKARAYI | F65: 9977096885 | K65: 0 | M65: 0
B66: 5 | C66: 19273 | D66: DINESH RAGHUWANSHI | E66: KAKARAYI | F66: 9977096885 | K66: 0 | M66: 0
H67: . | I67: 12 | K67: 4.8 | L67: 26400
H69: . | K69: Remark-
H70: . | K70: VS | L70: Total | M70: 26400
H71: . | K71: VS | M71: 2400
H72: . | L72: Bill amount | M72: 24000
H73: . | L73: Advance
H74: . | L74: Account Pay | M74: 24000
H75: . | L75: Cash Taken | M75: 0
H76: कृषक के हस्ताक्षर | J76: वास्ते वसुंधरा सीड्स | L76: Difference | M76: 0
C77: HI-1650 ( पूसा ओजस्वी) 40 KG | D77: TL | F77: KG
C78: HI-8826 40 KG | D78: TL | F78: KG
C79: HI-8826 50 KG | D79: TL | F79: KG
C80: C-306 40 KG | D80: TL | F80: KG
C81: GW-322 40 KG | D81: TL | F81: KG
C82: HI-1544 (पूर्णा) 40 KG | D82: TL | F82: KG
C83: HI-8663 (पोषण ) 40 KG | D83: TL | F83: KG
C84: HI-8713 (पूसा मंगल) 40 KG | D84: TL | F84: KG
C85: HI-8759 ( पूसा तेजस) 40 KG | D85: TL | F85: KG
C86: PRADHAN ( प्रधान) 40 KG | D86: TL | F86: KG
C87: cg-1044 50 KG | D87: TL | F87: KG
C88: phule vikrant 50 KG | D88: TL | F88: KG
... C143: HI-1655 ( पूसा हर्षा) BREEDER | D143: VS | F143: ER
C144: 0 | F144: 0
C145: 0 | F145: 0
C146: 0 | F146: 0
C147: 0 | F147: 0
C148: 0 | F148: 0
C149: 0 | F149: 0
C150: 0 | F150: 0
C151: 0 | F151: 0

Sheet Invoice2
J3: 52, RAJASWA COLONY,TANKI PATH FREEGANJ, UJJAIN MP
J4: PH 0734-2530547,9425332517 | X4: crt + L
J5: SEED LIC NO- 1178
B6: नाम | G6: Name | H6: DKSNDN | K6: Invoice no | L6: =MAXIFS(Sale!C:C,Sale!A:A,A10)+1 -> 2
B7: ग्राम | G7: Village | H7: DSDS | K7: Date | L7: 13-09-2025
B8: मोबाईल | G8: Phone no | H8: DSDS | K8: GST EXEMPTED WHEAT SEED
B9: Sno | C9: Invoice no | D9: Customer name | E9: Village | F9: Mobile No | G9: remark | H9: Particular | I9: Bags | J9: Packing | K9: Quantity | L9: Rate | M9: Amount | N9: TOTAL BILL AMOUT | O9: Discoumt | P9: GRAND TOTAL | Q9: Advance | R9: Card Pay | S9: CASH TAKEN | T9: Difference | U9: Remark | V9: date | W9: BAG STOCK | X9: QTL STOCK
A10: =K$19 -> #N/A | B10: 1 | C10: =L$6 -> 2 | D10: =H$6 -> DKSNDN | E10: =H$7 -> DSDS | F10: =H$8 -> DSDS | G10: =L17 | H10: HI-8759 ( पूसा तेजस) APR-2024-12-763-135644-FI | I10: 12 | J10: =if(H10>0,40,"") -> 40 | K10: =IFERROR(I10*J10/100,".") -> 4.8 | L10: =iferror(VLOOKUP(H10,Table2[[Variety]:[RATE]],5,false),"") | M10: =iferror(L10*K10, "") -> 0 | N10: =M18 -> 0 | O10: =M19 | P10: =M20 -> 0 | Q10: =M21 | R10: =M22 | S10: =M23 -> 0 | T10: =M24 -> 0 | U10: =K18 -> VS | V10: =L$7 -> 13-09-2025 | W10: =VLOOKUP(H10,Table2[[Variety]:[In Stock]],4,false)-I10 -> #N/A | X10: =W10/0.4 -> #N/A
A11: =K$19 -> #N/A | B11: 2 | C11: =L$6 -> 2 | D11: =H$6 -> DKSNDN | E11: =H$7 -> DSDS | F11: =H$8 -> DSDS | J11: =if(H11>0,40,"") | K11: =IFERROR(I11*J11/100,".") -> 0 | L11: =iferror(VLOOKUP(H11,Table2[[Variety]:[RATE]],5,false),"") | M11: =iferror(L11*K11, "") -> 0 | V11: =L$7 -> 13-09-2025 | W11: =VLOOKUP(H11,Table2[[Variety]:[In Stock]],4,false)-I11 -> #N/A | X11: =W11/0.4 -> #N/A
A12: =K$19 -> #N/A | B12: 3 | C12: =L$6 -> 2 | D12: =H$6 -> DKSNDN | E12: =H$7 -> DSDS | F12: =H$8 -> DSDS | J12: =if(H12>0,40,"") | K12: =IFERROR(I12*J12/100,"") -> 0 | L12: =iferror(VLOOKUP(H12,Table2[[Variety]:[RATE]],5,false),"") | M12: =iferror(L12*K12, "") -> 0 | V12: =L$7 -> 13-09-2025 | W12: =VLOOKUP(H12,Table2[[Variety]:[In Stock]],4,false)-I12 -> #N/A | X12: =W12/0.4 -> #N/A
A13: =K$19 -> #N/A | B13: 4 | C13: =L$6 -> 2 | D13: =H$6 -> DKSNDN | E13: =H$7 -> DSDS | F13: =H$8 -> DSDS | J13: =if(H13>0,40,"") | K13: =IFERROR(I13*J13/100,"") -> 0 | L13: =iferror(VLOOKUP(H13,Table2[[Variety]:[RATE]],5,false),"") | M13: =iferror(L13*K13, "") -> 0 | V13: =L$7 -> 13-09-2025 | W13: =VLOOKUP(H13,Table2[[Variety]:[In Stock]],4,false)-I13 -> #N/A | X13: =W13/0.4 -> #N/A
A14: =K$19 -> #N/A | B14: 5 | C14: =L$6 -> 2 | D14: =H$6 -> DKSNDN | E14: =H$7 -> DSDS | F14: =H$8 -> DSDS | J14: =if(H14>0,40,"") | K14: =IFERROR(I14*J14/100,"") -> 0 | L14: =iferror(VLOOKUP(H14,Table2[[Variety]:[RATE]],5,false),"") | M14: =iferror(L14*K14, "") -> 0 | V14: =L$7 -> 13-09-2025 | W14: =VLOOKUP(H14,Table2[[Variety]:[In Stock]],4,false)-I14 -> #N/A | X14: =W14/0.4 -> #N/A
H15: . | I15: =sum(I10:I14) -> 12 | K15: =sum(K10:K14) -> 4.8 | L15: =sum(M10:M14) -> 0 | W15: Diff | X15: 0
H17: . | K17: Remark- | X17: =sum(Y18:Y24) -> 0
H18: . | K18: =IF(M36=0,IF(M34>0,"BANK-VS","VS"),"Credit-vs") -> VS | L18: Total | M18: =L15 -> 0 | W18: 2000
H19: . | K19: =VLOOKUP(H10,Table2[],10,false) -> #N/A | W19: 500
H20: . | L20: Bill amount | M20: =M18-M19 -> 0 | W20: 200
H21: . | L21: Advance | W21: 100
H22: . | L22: Account Pay | W22: 50
H23: . | L23: Cash Taken | M23: =X17 -> 0 | W23: 20
H24: कृषक के हस्ताक्षर | J24: वास्ते वसुंधरा सीड्स | L24: Difference | M24: =M20-M21-M22-M23 -> 0 | W24: 10
C25: .
C26: .
C27: HI-8777 PUSA GEHU APR-2024-12-763-135627-FI-(I) | D27: VS | F27: I)
C28: GW-513 APR-2024-12-763-135624-FII-(I)-A | D28: VS | F28: -A
C29: GW-513 APR-2024-12-763-135624-FII-(I)-B | D29: VS | F29: -B
C30: GW-513 APR-2024-12-763-135624-FII-(II) | D30: VS | F30: I)
C31: HI-1544 (पूर्णा) APR-2024-12-763-135662-FI | D31: VS | F31: FI
C32: C-306 APR-2024-12-763-135670-FI | D32: VS | F32: FI
C33: HI-8830 (पूसा किर्ति) APR-2024-12-763-135635-FI-A | D33: VS | F33: -A
C34: HI-8830 (पूसा किर्ति) APR-2024-12-763-135635-FI-B | D34: VS | F34: -B
C35: HI-8663 (पोषण ) APR-2024-12-763-135628-FI-B | D35: VS | F35: -B
C36: LOK-1 APR-2024-12-763-135669-FI-A | D36: VS | F36: -A
C37: LOK-1 APR-2024-12-763-135668-FI-A | D37: VS | F37: -A
C38: LOK-1 APR-2024-12-763-135667-FI-A | D38: VS | F38: -A
... C52: HI-8830 (पूसा किर्ति) 40 KG | D52: TL | F52: KG
C53: GW-513 40 KG | D53: TL | F53: KG | H53: `
C54: HI-1650 ( पूसा ओजस्वी) APR-2024-12-763-135654-FI-A | D54: VS | F54: -A
C55: HI-1650 ( पूसा ओजस्वी) APR-2024-12-763-135654-FI-B | D55: VS | F55: -B
C56: HI-1636 ( पूसा वकुला) APR-2024-12-763-135660-FI | D56: VS | F56: FI
C57: GW-322 APR-2024-12-763-135637-FII-B | D57: VS | F57: -B
C58: GW-322 APR-2024-12-763-135653-FII-B | D58: VS | F58: -B
C59: GW-322 APR-2024-12-763-135653-FII-A | D59: VS | F59: -A
C60: HI-1650 ( पूसा ओजस्वी) APR-2024-12-763-135625-FI-A | D60: VS | F60: -A
C61: HI-1634 ( पूसा अहिल्या) 40 KG | D61: TL | F61: KG
C62: HI-8759 ( पूसा तेजस) APR-2024-12-763-135644-FI | D62: VS | F62: FI
C63: HI-1655 ( पूसा हर्षा) 40 KG | D63: TL | F63: KG
C64: HI-1634 ( पूसा अहिल्या) APR-2024-12-763-135651-FI-A | D64: VS | F64: -A
C65: HD-4728 (पूसा मालवी) APR-2024-12-763-135648-FII | D65: VS | F65: II
... C143: HI-1655 ( पूसा हर्षा) BREEDER | D143: VS | F143: ER
C144: 0 | F144: 0
C145: 0 | F145: 0
C146: 0 | F146: 0
C147: 0 | F147: 0
C148: 0 | F148: 0
C149: 0 | F149: 0
C150: 0 | F150: 0
C151: 0 | F151: 0

Sheet Sale
A1: Column1 | B1: Invoice no | C1: Customer name | D1: Village | E1: Mobile No | F1: remark | G1: Lot No | H1: Bags | I1: Weight | J1: Quantity | K1: Rate | L1: Amount | M1: TOTAL BILL AMOUT | N1: Discoumt | O1: GRAND TOTAL | P1: Card Pay | Q1: CASH TAKEN | R1: Difference | S1: Remark2 | T1: Date | U1: Remark2 | V1: Date
A2: TL | B2: 1 | C2: 8846 | H2: GW-513 40KG | I2: 5 | J2: 40 | K2: 2 | L2: 5300 | M2: 10600 | N2: 31800 | P2: 31800 | S2: 0 | T2: 31800 | U2: VS | V2: 13-09-2025 | W2: 1631 | X2: 4077.5
A3: TL | B3: 2 | C3: 8846 | H3: HI-1655(पूसा हर्षा) 40KG | I3: 10 | J3: 40 | K3: 4 | L3: 5300 | M3: 21200 | V3: 13-09-2025 | W3: 322 | X3: 805
A4: TL | B4: 3 | C4: 8846 | H4: JKG 5 KABULI 50KG | J4: 40 | K4: 0 | L4: 12000 | M4: 0 | V4: 13-09-2025 | W4: 60 | X4: 150
A5: TL | B5: 4 | C5: 8846 | K5: 0 | M5: 0 | V5: 13-09-2025 | W5: #N/A | X5: #N/A
A6: TL | B6: 5 | C6: 8846 | K6: 0 | M6: 0 | V6: 13-09-2025 | W6: #N/A | X6: #N/A
A7: #N/A | B7: 1 | C7: 1 | K7: 0 | M7: 0 | N7: 0 | P7: 0 | S7: 0 | T7: 0 | U7: VS | V7: 13-09-2025 | W7: #N/A | X7: #N/A
A8: #N/A | B8: 2 | C8: 1 | K8: 0 | M8: 0 | V8: 13-09-2025 | W8: #N/A | X8: #N/A
A9: #N/A | B9: 3 | C9: 1 | K9: 0 | M9: 0 | V9: 13-09-2025 | W9: #N/A | X9: #N/A
A10: #N/A | B10: 4 | C10: 1 | K10: 0 | M10: 0 | V10: 13-09-2025 | W10: #N/A | X10: #N/A
A11: #N/A | B11: 5 | C11: 1 | K11: 0 | M11: 0 | V11: 13-09-2025 | W11: #N/A | X11: #N/A
A12: TL | B12: 1 | C12: 8846 | D12: DINESH RAGHUWANSHI | E12: KAKARAYI | F12: 9977096885 | H12: GW-513 40KG | I12: 5 | J12: 40 | K12: 2 | L12: 5300 | M12: 10600 | N12: 10600 | P12: 10600 | S12: 0 | T12: 10600 | U12: VS | V12: 13-09-2025 | W12: 1636 | X12: 4090
A13: TL | B13: 2 | C13: 8846 | D13: DINESH RAGHUWANSHI | E13: KAKARAYI | F13: 9977096885 | K13: 0 | M13: 0 | V13: 13-09-2025 | W13: #N/A | X13: #N/A
A14: TL | B14: 3 | C14: 8846 | D14: DINESH RAGHUWANSHI | E14: KAKARAYI | F14: 9977096885 | K14: 0 | M14: 0 | V14: 13-09-2025 | W14: #N/A | X14: #N/A
A15: TL | B15: 4 | C15: 8846 | D15: DINESH RAGHUWANSHI | E15: KAKARAYI | F15: 9977096885 | K15: 0 | M15: 0 | V15: 13-09-2025 | W15: #N/A | X15: #N/A
A16: TL | B16: 5 | C16: 8846 | D16: DINESH RAGHUWANSHI | E16: KAKARAYI | F16: 9977096885 | K16: 0 | M16: 0 | V16: 13-09-2025 | W16: #N/A | X16: #N/A
A17: VS | B17: 19273 | C17: DINESH RAGHUWANSHI | D17: KAKARAYI | E17: 9977096885 | G17: HI-1650(पूसा ओजस्वी) MAR-25-12-763-40(3) (FII) | H17: 10 | I17: 40 | J17: 4 | K17: 5500 | L17: 22000 | M17: 26400 | N17: 2400 | O17: 24000 | Q17: 24000 | R17: 0 | S17: 0 | T17: VS | U17: 13-09-2025 | V17: 365 | W17: 912.5
A18: VS | B18: 19273 | C18: DINESH RAGHUWANSHI | D18: KAKARAYI | E18: 9977096885 | G18: GW-513 MAR-25-12-763-20(2) (CI) | H18: 2 | I18: 40 | J18: 0.8 | K18: 5500 | L18: 4400 | U18: 13-09-2025 | V18: 211 | W18: 527.5
A19: VS | B19: 19273 | C19: DINESH RAGHUWANSHI | D19: KAKARAYI | E19: 9977096885 | J19: 0 | L19: 0 | U19: 13-09-2025 | V19: #N/A | W19: #N/A
A20: VS | B20: 19273 | C20: DINESH RAGHUWANSHI | D20: KAKARAYI | E20: 9977096885 | J20: 0 | L20: 0 | U20: 13-09-2025 | V20: #N/A | W20: #N/A
A21: VS | B21: 19273 | C21: DINESH RAGHUWANSHI | D21: KAKARAYI | E21: 9977096885 | J21: 0 | L21: 0 | U21: 13-09-2025 | V21: #N/A | W21: #N/A
A22: TL | B22: 8845 | C22: RAJPAL SINGH | D22: KACHNARIYA | E22: 9425915634 | F22: 0 | G22: 33-86 50KG | H22: 2 | I22: 50 | J22: 1 | K22: 5000 | L22: 5000 | M22: 5000 | N22: 500 | O22: 4500 | P22: 4500 | Q22: 0 | R22: 0 | S22: BANK-VS | T22: 21-11-2025
A23: TL | B23: 8845 | C23: RAJPAL SINGH | D23: KACHNARIYA | E23: 9425915634 | T23: 21-11-2025
A24: TL | B24: 8845 | C24: RAJPAL SINGH | D24: KACHNARIYA | E24: 9425915634 | T24: 21-11-2025
A25: TL | B25: 8845 | C25: RAJPAL SINGH | D25: KACHNARIYA | E25: 9425915634 | T25: 21-11-2025
A26: TL | B26: 8845 | C26: RAJPAL SINGH | D26: KACHNARIYA | E26: 9425915634 | T26: 21-11-2025
A27: TL | B27: 8844 | C27: RAJESH VISHWAKARMA | D27: NIMBODA | E27: 9893274817 | F27: 0 | G27: HI-8830(पूसा किर्ति) 40KG | H27: 3 | I27: 40 | J27: 1.2 | K27: 5300 | L27: 6360 | M27: 6360 | N27: 0 | O27: 6360 | P27: 6360 | Q27: 0 | R27: 0 | S27: BANK-VS | T27: 21-11-2025
A28: TL | B28: 8844 | C28: RAJESH VISHWAKARMA | D28: NIMBODA | E28: 9893274817 | T28: 21-11-2025
A29: TL | B29: 8844 | C29: RAJESH VISHWAKARMA | D29: NIMBODA | E29: 9893274817 | T29: 21-11-2025
A30: TL | B30: 8844 | C30: RAJESH VISHWAKARMA | D30: NIMBODA | E30: 9893274817 | T30: 21-11-2025
A31: TL | B31: 8844 | C31: RAJESH VISHWAKARMA | D31: NIMBODA | E31: 9893274817 | T31: 21-11-2025
A32: TL | B32: 8843 | C32: AMAN SHARMA | D32: SUTLI | E32: 8643030828 | F32: 0 | G32: HI-1650(पूसा ओजस्वी) 40KG | H32: 1 | I32: 40 | J32: 0.4 | K32: 5300 | L32: 2120 | M32: 2120 | N32: 120 | O32: 2000 | P32: 0 | Q32: 2000 | R32: 0 | S32: VS | T32: 21-11-2025
A33: TL | B33: 8843 | C33: AMAN SHARMA | D33: SUTLI | E33: 8643030828 | T33: 21-11-2025
A34: TL | B34: 8843 | C34: AMAN SHARMA | D34: SUTLI | E34: 8643030828 | T34: 21-11-2025
A35: TL | B35: 8843 | C35: AMAN SHARMA | D35: SUTLI | E35: 8643030828 | T35: 21-11-2025
A36: TL | B36: 8843 | C36: AMAN SHARMA | D36: SUTLI | E36: 8643030828 | T36: 21-11-2025
A37: TL | B37: 8842 | C37: KAMALS SINGH | D37: LABAYCHYA | E37: 9907257138 | F37: 0 | G37: HI-8830(पूसा किर्ति) 40KG | H37: 3 | I37: 40 | J37: 1.2 | K37: 5300 | L37: 6360 | M37: 6360 | N37: 560 | O37: 5800 | P37: 0 | Q37: 5800 | R37: 0 | S37: VS | T37: 21-11-2025
A38: TL | B38: 8842 | C38: KAMALS SINGH | D38: LABAYCHYA | E38: 9907257138 | T38: 21-11-2025
A39: TL | B39: 8842 | C39: KAMALS SINGH | D39: LABAYCHYA | E39: 9907257138 | T39: 21-11-2025
A40: TL | B40: 8842 | C40: KAMALS SINGH | D40: LABAYCHYA | E40: 9907257138 | T40: 21-11-2025
A41: TL | B41: 8842 | C41: KAMALS SINGH | D41: LABAYCHYA | E41: 9907257138 | T41: 21-11-2025
A42: VS | B42: 19272 | C42: GANESH | D42: BORDA MANDA | E42: 0 | F42: 0 | G42: LOK-1 APR-25-12-763-9(2) (FI) | H42: 1 | I42: 40 | J42: 0.4 | K42: 5500 | L42: 2200 | M42: 2200 | N42: 0 | O42: 2200 | P42: 0 | Q42: 2200 | R42: 0 | S42: VS | T42: 21-11-2025
A43: VS | B43: 19272 | C43: GANESH | D43: BORDA MANDA | E43: 0 | T43: 21-11-2025
A44: VS | B44: 19272 | C44: GANESH | D44: BORDA MANDA | E44: 0 | T44: 21-11-2025
A45: VS | B45: 19272 | C45: GANESH | D45: BORDA MANDA | E45: 0 | T45: 21-11-2025
A46: VS | B46: 19272 | C46: GANESH | D46: BORDA MANDA | E46: 0 | T46: 21-11-2025
A47: TL | B47: 8841 | C47: GOVIND CHOUHAN | D47: BICHROD | E47: 9131156877 | F47: 0 | G47: PRADHAN(प्रधान) 40KG | H47: 5 | I47: 40 | J47: 2 | K47: 5000 | L47: 10000 | M47: 10000 | N47: 0 | O47: 10000 | P47: 0 | Q47: 10000 | R47: 0 | S47: VS | T47: 20-11-2025
A48: TL | B48: 8841 | C48: GOVIND CHOUHAN | D48: BICHROD | E48: 9131156877 | T48: 20-11-2025
A49: TL | B49: 8841 | C49: GOVIND CHOUHAN | D49: BICHROD | E49: 9131156877 | T49: 20-11-2025
A50: TL | B50: 8841 | C50: GOVIND CHOUHAN | D50: BICHROD | E50: 9131156877 | T50: 20-11-2025
A51: TL | B51: 8841 | C51: GOVIND CHOUHAN | D51: BICHROD | E51: 9131156877 | T51: 20-11-2025
A52: VS | B52: 19271 | C52: NISAR KHAN | D52: SEONI MP | E52: 9575308599 | F52: R S SOLSINDA | G52: HI-1650(पूसा ओजस्वी) APR-25-12-763-45 (FII) | H52: 2 | I52: 40 | J52: 0.8 | K52: 5500 | L52: 4400 | M52: 4400 | N52: 0 | O52: 4400 | P52: 0 | Q52: 0 | R52: 4400 | S52: Credit-vs | T52: 20-11-2025
A53: VS | B53: 19271 | C53: NISAR KHAN | D53: SEONI MP | E53: 9575308599 | T53: 20-11-2025
A54: VS | B54: 19271 | C54: NISAR KHAN | D54: SEONI MP | E54: 9575308599 | T54: 20-11-2025
A55: VS | B55: 19271 | C55: NISAR KHAN | D55: SEONI MP | E55: 9575308599 | T55: 20-11-2025
A56: VS | B56: 19271 | C56: NISAR KHAN | D56: SEONI MP | E56: 9575308599 | T56: 20-11-2025
A57: VS | B57: 19270 | C57: ANANDI LAL BHATI | D57: TARANA KHATRI | E57: 9752977001 | F57: 0 | G57: HI-8830(पूसा किर्ति) APR-2024-12-763-135647-FI-A | H57: 2 | I57: 40 | J57: 0.8 | K57: 7500 | L57: 6000 | M57: 6000 | N57: 0 | O57: 6000 | P57: 6000 | Q57: 0 | R57: 0 | S57: BANK-VS | T57: 20-11-2025
A58: VS | B58: 19270 | C58: ANANDI LAL BHATI | D58: TARANA KHATRI | E58: 9752977001 | T58: 20-11-2025
A59: VS | B59: 19270 | C59: ANANDI LAL BHATI | D59: TARANA KHATRI | E59: 9752977001 | T59: 20-11-2025
A60: VS | B60: 19270 | C60: ANANDI LAL BHATI | D60: TARANA KHATRI | E60: 9752977001 | T60: 20-11-2025
A61: VS | B61: 19270 | C61: ANANDI LAL BHATI | D61: TARANA KHATRI | E61: 9752977001 | T61: 20-11-2025
A62: VS | B62: 19269 | C62: 0 | D62: 0 | E62: 0 | F62: 0 | M62: 0 | N62: 0 | O62: 0 | P62: 0 | Q62: 0 | R62: 0 | S62: VS | T62: 20-11-2025
A63: VS | B63: 19269 | C63: 0 | D63: 0 | E63: 0 | T63: 20-11-2025
A64: VS | B64: 19269 | C64: 0 | D64: 0 | E64: 0 | T64: 20-11-2025
A65: VS | B65: 19269 | C65: 0 | D65: 0 | E65: 0 | T65: 20-11-2025
A66: VS | B66: 19269 | C66: 0 | D66: 0 | E66: 0 | T66: 20-11-2025
A67: TL | B67: 8840 | C67: SOHAN SINGH | D67: AKIYA JASSA | E67: 7067040980 | F67: 0 | G67: HI-1650(पूसा ओजस्वी) 40KG | H67: 3 | I67: 40 | J67: 1.2 | K67: 5300 | L67: 6360 | M67: 6360 | N67: 0 | O67: 6360 | P67: 0 | Q67: 6360 | R67: 0 | S67: VS | T67: 20-11-2025
A68: TL | B68: 8840 | C68: SOHAN SINGH | D68: AKIYA JASSA | E68: 7067040980 | T68: 20-11-2025
A69: TL | B69: 8840 | C69: SOHAN SINGH | D69: AKIYA JASSA | E69: 7067040980 | T69: 20-11-2025
A70: TL | B70: 8840 | C70: SOHAN SINGH | D70: AKIYA JASSA | E70: 7067040980 | T70: 20-11-2025
A71: TL | B71: 8840 | C71: SOHAN SINGH | D71: AKIYA JASSA | E71: 7067040980 | T71: 20-11-2025
A72: TL | B72: 8839 | C72: BHERULAL JI SHARMA | D72: KHORIYA | E72: 9516829378 | F72: 0 | G72: HI-8713(पूसा मंगल) 40KG | H72: 2 | I72: 40 | J72: 0.8 | K72: 5300 | L72: 4240 | M72: 4240 | N72: 0 | O72: 4240 | P72: 0 | Q72: 4240 | R72: 0 | S72: VS | T72: 20-11-2025
A73: TL | B73: 8839 | C73: BHERULAL JI SHARMA | D73: KHORIYA | E73: 9516829378 | T73: 20-11-2025
A74: TL | B74: 8839 | C74: BHERULAL JI SHARMA | D74: KHORIYA | E74: 9516829378 | T74: 20-11-2025
A75: TL | B75: 8839 | C75: BHERULAL JI SHARMA | D75: KHORIYA | E75: 9516829378 | T75: 20-11-2025
A76: TL | B76: 8839 | C76: BHERULAL JI SHARMA | D76: KHORIYA | E76: 9516829378 | T76: 20-11-2025
A77: VS | B77: 19268 | C77: SHUBHAM | D77: MADHOPURA | E77: 8319272965 | F77: 0 | G77: GW-513 MAR-25-12-763-20 (CI) | H77: 2 | I77: 40 | J77: 0.8 | K77: 5500 | L77: 4400 | M77: 4400 | N77: 0 | O77: 4400 | P77: 4400 | Q77: 0 | R77: 0 | S77: BANK-VS | T77: 20-11-2025
A78: VS | B78: 19268 | C78: SHUBHAM | D78: MADHOPURA | E78: 8319272965 | T78: 20-11-2025
A79: VS | B79: 19268 | C79: SHUBHAM | D79: MADHOPURA | E79: 8319272965 | T79: 20-11-2025
A80: VS | B80: 19268 | C80: SHUBHAM | D80: MADHOPURA | E80: 8319272965 | T80: 20-11-2025
A81: VS | B81: 19268 | C81: SHUBHAM | D81: MADHOPURA | E81: 8319272965 | T81: 20-11-2025
A82: TL | B82: 8838 | C82: DINESH CHOUHAN | D82: MATANA /INDORE ROAD | E82: 6232583115 | F82: 0 | G82: HI-8830(पूसा किर्ति) 40KG | H82: 3 | I82: 40 | J82: 1.2 | K82: 5300 | L82: 6360 | M82: 6360 | N82: 0 | O82: 6360 | P82: 0 | Q82: 6360 | R82: 0 | S82: VS | T82: 20-11-2025
A83: TL | B83: 8838 | C83: DINESH CHOUHAN | D83: MATANA /INDORE ROAD | E83: 6232583115 | T83: 20-11-2025
A84: TL | B84: 8838 | C84: DINESH CHOUHAN | D84: MATANA /INDORE ROAD | E84: 6232583115 | T84: 20-11-2025
A85: TL | B85: 8838 | C85: DINESH CHOUHAN | D85: MATANA /INDORE ROAD | E85: 6232583115 | T85: 20-11-2025
A86: TL | B86: 8838 | C86: DINESH CHOUHAN | D86: MATANA /INDORE ROAD | E86: 6232583115 | T86: 20-11-2025
A87: TL | B87: 8837 | C87: MAYARAM | D87: SABUKHEDI | E87: 0 | F87: 0 | G87: PRADHAN(प्रधान) 40KG | H87: 1 | I87: 40 | J87: 0.4 | K87: 5000 | L87: 2000 | M87: 2000 | N87: 0 | O87: 2000 | P87: 0 | Q87: 2000 | R87: 0 | S87: VS | T87: 20-11-2025
A88: TL | B88: 8837 | C88: MAYARAM | D88: SABUKHEDI | E88: 0 | T88: 20-11-2025
A89: TL | B89: 8837 | C89: MAYARAM | D89: SABUKHEDI | E89: 0 | T89: 20-11-2025
A90: TL | B90: 8837 | C90: MAYARAM | D90: SABUKHEDI | E90: 0 | T90: 20-11-2025
A91: TL | B91: 8837 | C91: MAYARAM | D91: SABUKHEDI | E91: 0 | T91: 20-11-2025
A92: TL | B92: 8836 | C92: ROHIT PATEL | D92: UPADI | E92: 9826948499 | F92: 0 | G92: HI-8830(पूसा किर्ति) 40KG | H92: 2 | I92: 40 | J92: 0.8 | K92: 5300 | L92: 4240 | M92: 4240 | N92: 40 | O92: 4200 | P92: 4200 | Q92: 0 | R92: 0 | S92: BANK-VS | T92: 20-11-2025
A93: TL | B93: 8836 | C93: ROHIT PATEL | D93: UPADI | E93: 9826948499 | T93: 20-11-2025
A94: TL | B94: 8836 | C94: ROHIT PATEL | D94: UPADI | E94: 9826948499 | T94: 20-11-2025
A95: TL | B95: 8836 | C95: ROHIT PATEL | D95: UPADI | E95: 9826948499 | T95: 20-11-2025
A96: TL | B96: 8836 | C96: ROHIT PATEL | D96: UPADI | E96: 9826948499 | T96: 20-11-2025
A97: TL | B97: 8835 | C97: RAJVARDHAN SINGH | D97: AASER | E97: 6260456427 | F97: 0 | G97: HI-8830(पूसा किर्ति) 40KG | H97: 1 | I97: 40 | J97: 0.4 | K97: 5300 | L97: 2120 | M97: 2120 | N97: 20 | O97: 2100 | P97: 0 | Q97: 2100 | R97: 0 | S97: VS | T97: 20-11-2025
A98: TL | B98: 8835 | C98: RAJVARDHAN SINGH | D98: AASER | E98: 6260456427 | T98: 20-11-2025
A99: TL | B99: 8835 | C99: RAJVARDHAN SINGH | D99: AASER | E99: 6260456427 | T99: 20-11-2025
A100: TL | B100: 8835 | C100: RAJVARDHAN SINGH | D100: AASER | E100: 6260456427 | T100: 20-11-2025
...

Sheet Purchase
B4: Date | C4: Column3 | D4: Lot No | E4: Variety | F4: Bags | G4: Weight | H4: Quantity | I4: Column1 | J4: Column2 | K4: RATE
B5: 45912 | C5: GW-513 | D5: MAR-25-12-763-20 (CI) | E5: GW-513 MAR-25-12-763-20 (CI) | F5: 300 | G5: 40 | H5: 120 | I5: 5500 | K5: MP
B6: 45912 | C6: GW-513 | D6: MAR-25-12-763-20(2) (CI) | E6: GW-513 MAR-25-12-763-20(2) (CI) | F6: 163 | G6: 40 | H6: 65.2 | I6: 5500 | K6: MP
B7: 45912 | C7: GW-513 | D7: MAR-25-12-763-20 (CI) | E7: GW-513 MAR-25-12-763-20 (CI) | F7: 145 | G7: 40 | H7: 58 | I7: 5500 | K7: MP
B8: 45912 | C8: GW-322 | D8: MAR-25-12-763-49 (CI) | E8: GW-322 MAR-25-12-763-49 (CI) | F8: 300 | G8: 40 | H8: 120 | I8: 5500 | K8: GD
B9: 45912 | C9: GW-322 | D9: MAR-25-12-763-50 (CI) | E9: GW-322 MAR-25-12-763-50 (CI) | F9: 162 | G9: 40 | H9: 64.8 | I9: 5500 | K9: GD
B10: 45913 | C10: GW-322 | D10: MAR-25-12-763-49 (CI) | E10: GW-322 MAR-25-12-763-49 (CI) | F10: 138 | G10: 40 | H10: 55.2 | I10: 5500 | K10: GD
B11: 45913 | C11: GW-322 | D11: MAR-25-12-763-50 (CI) | E11: GW-322 MAR-25-12-763-50 (CI) | F11: 197 | G11: 40 | H11: 78.8 | I11: 5500 | K11: GD
B12: 45913 | C12: GW-513 | D12: 40KG | E12: GW-513 40KG | F12: 65 | G12: 40 | H12: 26 | I12: 5300 | K12: MP
B13: 45915 | C13: HD-4728(पूसा मालवी) | D13: MAR-25-12-763-38 (CI) | E13: HD-4728(पूसा मालवी) MAR-25-12-763-38 (CI) | F13: 300 | G13: 40 | H13: 120 | I13: 5500 | K13: SB
B14: 45915 | C14: HD-4728(पूसा मालवी) | D14: MAR-25-12-763-38 (CI) | E14: HD-4728(पूसा मालवी) MAR-25-12-763-38 (CI) | F14: 142 | G14: 40 | H14: 56.8 | I14: 5500 | K14: SB
B15: 45915 | C15: HD-4728(पूसा मालवी) | D15: MAR-25-12-763-37 (CI) | E15: HD-4728(पूसा मालवी) MAR-25-12-763-37 (CI) | F15: 82 | G15: 40 | H15: 32.8 | I15: 5500 | K15: SB
B16: 45915 | C16: GW-322 | D16: 40KG | E16: GW-322 40KG | F16: 76 | G16: 40 | H16: 30.4 | I16: 5300 | K16: GD
... B39: 45925 | C39: HI-8713(पूसा मंगल) | D39: MAR-25-12-763-36(2) (FII) | E39: HI-8713(पूसा मंगल) MAR-25-12-763-36(2) (FII) | F39: 97 | G39: 40 | H39: 38.8 | I39: 5500 | K39: JA
B40: 45927 | C40: 8826 | D40: 40KG | E40: 8826 40KG | F40: 209 | G40: 40 | H40: 83.6 | I40: 5000 | K40: GL
B41: 45927 | C41: 8826 | D41: 40KG | E41: 8826 40KG | F41: 99 | G41: 40 | H41: 39.6 | I41: 5000 | K41: RB
B42: 45927 | C42: HI-1655(पूसा हर्षा) | D42: 40KG | E42: HI-1655(पूसा हर्षा) 40KG | F42: 332 | G42: 40 | H42: 132.8 | I42: 5300 | K42: MIX
B43: 45927 | C43: HI-1655(पूसा हर्षा) | D43: MAR-25-12-763-21 (FI) | E43: HI-1655(पूसा हर्षा) MAR-25-12-763-21 (FI) | F43: 110 | G43: 40 | H43: 44 | I43: 5500 | K43: VS
B44: 45927 | C44: 8826 | D44: 40KG | E44: 8826 40KG | F44: 46 | G44: 40 | H44: 18.4 | I44: 5000 | K44: GL
B45: 45927 | C45: HI-1650(पूसा ओजस्वी) | D45: 40KG | E45: HI-1650(पूसा ओजस्वी) 40KG | F45: 149 | G45: 40 | H45: 59.6 | I45: 5300 | K45: 0
C46: HI-1634(पूसा अहिल्या) | D46: 40KG | E46: HI-1634(पूसा अहिल्या) 40KG | F46: 1222 | G46: 40 | H46: 488.8 | I46: 5300 | K46: IS
C47: HD-3385 | D47: 40KG | E47: HD-3385 40KG | F47: 863 | G47: 40 | H47: 345.2 | I47: 5300 | K47: AS
C48: HD-3385 | D48: 40KG | E48: HD-3385 40KG | F48: 376 | G48: 40 | H48: 150.4 | I48: 5300 | K48: BA
C49: HD-3385 | D49: 40KG | E49: HD-3385 40KG | F49: 1093 | G49: 40 | H49: 437.2 | I49: 5300 | K49: HR
C50: HD-3385 | D50: 40KG | E50: HD-3385 40KG | F50: 183 | G50: 40 | H50: 73.2 | I50: 5300 | K50: KR
C51: HD-3385 | D51: 40KG | E51: HD-3385 40KG | F51: 341 | G51: 40 | H51: 136.4 | I51: 5300 | K51: MS
C52: HD-3385 | D52: 40KG | E52: HD-3385 40KG | F52: 1240 | G52: 40 | H52: 496 | I52: 5300 | K52: RN
C53: HD-3385 | D53: 40KG | E53: HD-3385 40KG | F53: 1269 | G53: 40 | H53: 507.6 | I53: 5300 | K53: RS
C54: HD-3385 | D54: 40KG | E54: HD-3385 40KG | F54: 66 | G54: 40 | H54: 26.4 | I54: 5300 | K54: RR
C55: 33-88 40KG | E55: 33-88 40KG | F55: 230 | G55: 40 | H55: 92 | I55: 5000 | K55: DD
C56: 3390 40KG | E56: 3390 40KG | F56: 154 | G56: 40 | H56: 61.6 | I56: 5000 | K56: RR
C57: 3390 40KG | E57: 3390 40KG | F57: 410 | G57: 40 | H57: 164 | I57: 5000 | K57: SN
C58: HD-3410 | D58: 40KG | E58: HD-3410 40KG | F58: 272 | G58: 40 | H58: 108.8 | I58: 5300 | K58: DP
C59: HD-3410 | D59: 40KG | E59: HD-3410 40KG | F59: 137 | G59: 40 | H59: 54.8 | I59: 5300 | K59: JD
C60: HD-3410 | D60: 40KG | E60: HD-3410 40KG | F60: 26 | G60: 40 | H60: 10.4 | I60: 5300 | K60: RR
C61: HD-3410 | D61: 40KG | E61: HD-3410 40KG | F61: 349 | G61: 40 | H61: 139.6 | I61: 5300 | K61: SN
C62: HI-8830(पूसा किर्ति) | D62: 40KG | E62: HI-8830(पूसा किर्ति) 40KG | F62: 482 | G62: 40 | H62: 192.8 | I62: 5300 | K62: DS
C63: HI-8830(पूसा किर्ति) | D63: 40KG | E63: HI-8830(पूसा किर्ति) 40KG | F63: 1073 | G63: 40 | H63: 429.2 | I63: 5300 | K63: KB
C64: HI-8830(पूसा किर्ति) | D64: 40KG | E64: HI-8830(पूसा किर्ति) 40KG | F64: 673 | G64: 40 | H64: 269.2 | I64: 5300 | K64: 3
C65: HI-8830(पूसा किर्ति) | D65: 40KG | E65: HI-8830(पूसा किर्ति) 40KG | F65: 358 | G65: 40 | H65: 143.2 | I65: 5300 | K65: RB
C66: HI-8830(पूसा किर्ति) | D66: 40KG | E66: HI-8830(पूसा किर्ति) 40KG | F66: 2610 | G66: 40 | H66: 1044 | I66: 5300 | K66: RS
C67: HD-3385 BR | D67: 40KG | E67: HD-3385 BR 40KG | F67: 110 | G67: 40 | H67: 44 | I67: 7000 | K67: MG
C68: HD-3385 BR | D68: 40KG | E68: HD-3385 BR 40KG | F68: 149 | G68: 40 | H68: 59.6 | I68: 7000 | K68: RR
C69: C-306 | D69: 40KG | E69: C-306 40KG | F69: 51 | G69: 40 | H69: 20.4 | I69: 6000 | K69: BB
C70: C-306 | D70: 40KG | E70: C-306 40KG | F70: 480 | G70: 40 | H70: 192 | I70: 6000 | K70: JM
C71: C-306 | D71: 40KG | E71: C-306 40KG | F71: 314 | G71: 40 | H71: 125.6 | I71: 6000 | K71: KB
C72: HI-1650(पूसा ओजस्वी) | D72: 40KG | E72: HI-1650(पूसा ओजस्वी) 40KG | F72: 2412 | G72: 40 | H72: 964.8 | I72: 5300 | K72: 0
C73: HI-1650(पूसा ओजस्वी) | D73: 40KG | E73: HI-1650(पूसा ओजस्वी) 40KG | F73: 664 | G73: 40 | H73: 265.6 | I73: 5300
C74: HI-1650(पूसा ओजस्वी) | D74: 40KG | E74: HI-1650(पूसा ओजस्वी) 40KG | F74: 87 | G74: 40 | H74: 34.8 | I74: 5300 | K74: SN
C75: HI-1650(पूसा ओजस्वी) | D75: 40KG | E75: HI-1650(पूसा ओजस्वी) 40KG | F75: 379 | G75: 40 | H75: 151.6 | I75: 5300 | K75: SS
C76: LOK-1 | D76: 40KG | E76: LOK-1 40KG | F76: 284 | G76: 40 | H76: 113.6 | I76: 5300 | K76: BB
C77: LOK-1 | D77: 40KG | E77: LOK-1 40KG | F77: 404 | G77: 40 | H77: 161.6 | I77: 5300 | K77: KB
C78: PRADHAN(प्रधान) | D78: 40KG | E78: PRADHAN(प्रधान) 40KG | F78: 945 | G78: 40 | H78: 378 | I78: 5000
C79: MANAV(मानव) | D79: 40KG | E79: MANAV(मानव) 40KG | F79: 154 | G79: 40 | H79: 61.6 | I79: 12000
C80: SAMRUDDHI(समृद्धि) | D80: 40KG | E80: SAMRUDDHI(समृद्धि) 40KG | F80: 127 | G80: 40 | H80: 50.8 | I80: 8000
C81: HI-8759(पूसा तेजस) | D81: 40KG | E81: HI-8759(पूसा तेजस) 40KG | F81: 1136 | G81: 40 | H81: 454.4 | I81: 5300 | K81: DR
C82: HI-8759(पूसा तेजस) | D82: 40KG | E82: HI-8759(पूसा तेजस) 40KG | F82: 450 | G82: 40 | H82: 180 | I82: 5300 | K82: NH
B83: 45928 | C83: HI-8713(पूसा मंगल) | D83: MAR-25-12-763-36 (FII) | E83: HI-8713(पूसा मंगल) MAR-25-12-763-36 (FII) | F83: 78 | G83: 40 | H83: 31.2 | I83: 5500 | K83: IR
B84: 45928 | C84: HI-8713(पूसा मंगल) | D84: MAR-25-12-763-36 (FII) | E84: HI-8713(पूसा मंगल) MAR-25-12-763-36 (FII) | F84: 232 | G84: 40 | H84: 92.8 | I84: 5500 | K84: JA
B85: 45928 | C85: HI-8759(पूसा तेजस) | D85: MAR-25-12-763-52 (FII) | E85: HI-8759(पूसा तेजस) MAR-25-12-763-52 (FII) | F85: 280 | G85: 40 | H85: 112 | I85: 5500 | K85: NP
B86: 45928 | C86: HI-8759(पूसा तेजस) | D86: MAR-25-12-763-51 (FII) | E86: HI-8759(पूसा तेजस) MAR-25-12-763-51 (FII) | F86: 23 | G86: 40 | H86: 9.2 | I86: 5500 | K86: NP
B87: 45928 | C87: HI-8759(पूसा तेजस) | D87: MAR-25-12-763-51 (FII) | E87: HI-8759(पूसा तेजस) MAR-25-12-763-51 (FII) | F87: 300 | G87: 40 | H87: 120 | I87: 5500 | K87: NP
B88: 45928 | C88: HI-8759(पूसा तेजस) | D88: MAR-25-12-763-51 (FII) | E88: HI-8759(पूसा तेजस) MAR-25-12-763-51 (FII) | F88: 118 | G88: 40 | H88: 47.2 | I88: 5500 | K88: NP
B89: 45928 | C89: HI-8759(पूसा तेजस) | D89: MAR-25-12-763-52(2) (FII) | E89: HI-8759(पूसा तेजस) MAR-25-12-763-52(2) (FII) | F89: 222 | G89: 40 | H89: 88.8 | I89: 5500 | K89: NP
B90: 45929 | C90: HI-8759(पूसा तेजस) | D90: MAR-25-12-763-52(2) (FII) | E90: HI-8759(पूसा तेजस) MAR-25-12-763-52(2) (FII) | F90: 300 | G90: 40 | H90: 120 | I90: 5500 | K90: NP
B91: 45929 | C91: HI-8830(पूसा किर्ति) | D91: APR-25-12-763-28 (FII) | E91: HI-8830(पूसा किर्ति) APR-25-12-763-28 (FII) | F91: 300 | G91: 40 | H91: 120 | I91: 5500 | K91: RS
B92: 45929 | C92: HI-8830(पूसा किर्ति) | D92: APR-25-12-763-28(2) (FII) | E92: HI-8830(पूसा किर्ति) APR-25-12-763-28(2) (FII) | F92: 115 | G92: 40 | H92: 46 | I92: 5500 | K92: RS
B93: 45929 | C93: HI-8830(पूसा किर्ति) | D93: MAR-25-12-763-27(2) (FII) | E93: HI-8830(पूसा किर्ति) MAR-25-12-763-27(2) (FII) | F93: 233 | G93: 40 | H93: 93.2 | I93: 5500 | K93: RS
B94: 45930 | C94: HI-1634(पूसा अहिल्या) | D94: MAR-25-12-763-48 (FII) | E94: HI-1634(पूसा अहिल्या) MAR-25-12-763-48 (FII) | F94: 252 | G94: 40 | H94: 100.8 | I94: 5500 | K94: AS
... B99: 45932 | C99: HI-8713(पूसा मंगल) | D99: 40KG | E99: HI-8713(पूसा मंगल) 40KG | F99: 119 | G99: 40 | H99: 47.6 | I99: 5300 | K99: RJ
C100: DAFTARI 21 | D100: 10KG | E100: DAFTARI 21 10KG | F100: 300 | G100: 10 | H100: 30 | I100: 14000
B101: 45933 | E101: GW-513 40KG | F101: 100 | G101: 40 | H101: 40 | K101: WH
B102: 45933 | E102: HI-1650(पूसा ओजस्वी) 40KG | F102: 50 | G102: 40 | H102: 20 | K102: WH
B103: 45933 | E103: HI-8713(पूसा मंगल) 40KG | F103: 100 | G103: 40 | H103: 40 | K103: WH
B104: 45933 | E104: HI-8759(पूसा तेजस) 40KG | F104: 465 | G104: 40 | H104: 186 | K104: WH
B105: 45933 | E105: HI-8830(पूसा किर्ति) 40KG | F105: 100 | G105: 40 | H105: 40 | K105: WH
B106: 45933 | E106: LOK-1 MAR-25-12-763-18 (FI) | F106: 100 | G106: 40 | H106: 40 | K106: WH
B107: 45931 | C107: HI-1544 (पूर्णा) | D107: 40KG | E107: HI-1544 (पूर्णा) 40KG | F107: 564 | G107: 40 | H107: 225.6 | I107: 5300
B108: 45933 | C108: HI-8830(पूसा किर्ति) | D108: APR-25-12-763-31 (FII) | E108: HI-8830(पूसा किर्ति) APR-25-12-763-31 (FII) | F108: 161 | G108: 40 | H108: 64.4 | I108: 5500 | K108: RS
B109: 45933 | C109: HI-8830(पूसा किर्ति) | D109: MAR-25-12-763-27 (FII) | E109: HI-8830(पूसा किर्ति) MAR-25-12-763-27 (FII) | F109: 139 | G109: 40 | H109: 55.6 | I109: 5500 | K109: RS
B110: 45933 | C110: HI-1650(पूसा ओजस्वी) | D110: MAR-25-12-763-43 (FII) | E110: HI-1650(पूसा ओजस्वी) MAR-25-12-763-43 (FII) | F110: 300 | G110: 40 | H110: 120 | I110: 5500 | K110: BM
B111: 45933 | C111: 33-88 40KG | E111: 33-88 40KG | F111: 29 | G111: 40 | H111: 11.6 | I111: 5000 | K111: RR
C112: 16-69 | D112: 40KG | E112: 16-69 40KG | F112: 162 | G112: 40 | H112: 64.8 | I112: 8000 | K112: ASHARAM
B113: 45934 | C113: LOK-1 | D113: MAR-25-12-763-18 (FI) | E113: LOK-1 MAR-25-12-763-18 (FI) | F113: 106 | G113: 40 | H113: 42.4 | I113: 5500
B114: 45934 | C114: LOK-1 | D114: MAR-25-12-763-8 (FI) | E114: LOK-1 MAR-25-12-763-8 (FI) | F114: 244 | G114: 40 | H114: 97.6 | I114: 5500
B115: 45934 | E115: GW-513 40KG | F115: 150 | G115: 40 | H115: 60 | I115: 5300
B116: 45934 | E116: HI-1650(पूसा ओजस्वी) 40KG | F116: 50 | G116: 40 | H116: 20 | I116: 5300
B117: 45934 | E117: HI-8713(पूसा मंगल) 40KG | F117: 200 | G117: 40 | H117: 80 | I117: 5300
B118: 45934 | E118: HI-8759(पूसा तेजस) 40KG | F118: 465 | G118: 40 | H118: 186 | I118: 5300
B119: 45934 | E119: HI-8830(पूसा किर्ति) 40KG | F119: 100 | G119: 40 | H119: 40 | I119: 5300
B120: 45934 | E120: HI-8830(पूसा किर्ति) 40KG | F120: 250 | G120: 40 | H120: 100 | I120: 5300
B121: 45934 | E121: HI-1650(पूसा ओजस्वी) 40KG | F121: 100 | G121: 40 | H121: 40 | I121: 5300
B122: 45934 | E122: GW-513 40KG | F122: 50 | G122: 40 | H122: 20 | I122: 5300
B123: 45934 | E123: HI-8759(पूसा तेजस) 40KG | F123: 250 | G123: 40 | H123: 100 | I123: 5300
B124: 45935 | C124: HI-8759(पूसा तेजस) | D124: MAR-25-12-763-54(2) (FII) | E124: HI-8759(पूसा तेजस) MAR-25-12-763-54(2) (FII) | F124: 140 | G124: 40 | H124: 56 | I124: 5500 | K124: NP
B125: 45935 | C125: HI-8759(पूसा तेजस) | D125: MAR-25-12-763-54 (FII) | E125: HI-8759(पूसा तेजस) MAR-25-12-763-54 (FII) | F125: 200 | G125: 40 | H125: 80 | I125: 5500 | K125: NP
B126: 45936 | C126: HI-8759(पूसा तेजस) | D126: MAR-25-12-763-54 (FII) | E126: HI-8759(पूसा तेजस) MAR-25-12-763-54 (FII) | F126: 238 | G126: 40 | H126: 95.2 | I126: 5500 | K126: NP
B127: 45936 | C127: HI-8759(पूसा तेजस) | D127: MAR-25-12-763-52(2) (FII) | E127: HI-8759(पूसा तेजस) MAR-25-12-763-52(2) (FII) | F127: 62 | G127: 40 | H127: 24.8 | I127: 5500 | K127: AD
B128: 45936 | C128: HI-8759(पूसा तेजस) | D128: MAR-25-12-763-52 (FII) | E128: HI-8759(पूसा तेजस) MAR-25-12-763-52 (FII) | F128: 100 | G128: 40 | H128: 40 | I128: 5500 | K128: AD
B129: 45936 | C129: HI-8713(पूसा मंगल) | D129: 40KG | E129: HI-8713(पूसा मंगल) 40KG | F129: 245 | G129: 40 | H129: 98 | I129: 5500 | K129: PS
...

Sheet Inventory
B2: Variety | C2: Purchse Qty | D2: Sale Qty | E2: In Stock | F2: RATE | G2: Purchse Qty2 | H2: Sale Qty3 | I2: In Stock4 | J2: HOLD | K2: Column 1
B3: {=UNIQUE(Purchase!E5:E334)} -> GW-513 MAR-25-12-763-20 (CI) | C3: =sumif(Purchase!E$5:E1000,B3,Purchase!F$5:F1000) -> 445 | D3: =SUMIF(Sale!H:H,B3,Sale!I:I) -> 0 | E3: =C3-D3 -> 445 | F3: =VLOOKUP(B3,Table1[[Variety]:[Column1]],5,FALSE) -> 5500 | G3: =C3*0.4 -> 178 | H3: =D3*0.4 -> 0 | I3: =E3*0.4 -> 178 | K3: =IF(right(B3,2)="KG","TL","VS") -> VS
B4: GW-513 MAR-25-12-763-20(2) (CI) | C4: =sumif(Purchase!E$5:E1000,B4,Purchase!F$5:F1000) -> 213 | D4: =SUMIF(Sale!H:H,B4,Sale!I:I) -> 0 | E4: =C4-D4 -> 213 | F4: =VLOOKUP(B4,Table1[[Variety]:[Column1]],5,FALSE) -> 5500 | G4: =C4*0.4 -> 85.2 | H4: =D4*0.4 -> 0 | I4: =E4*0.4 -> 85.2 | K4: =IF(right(B4,2)="KG","TL","VS") -> VS
B5: GW-322 MAR-25-12-763-49 (CI) | C5: =sumif(Purchase!E$5:E1000,B5,Purchase!F$5:F1000) -> 438 | D5: =SUMIF(Sale!H:H,B5,Sale!I:I) -> 0 | E5: =C5-D5 -> 438 | F5: =VLOOKUP(B5,Table1[[Variety]:[Column1]],5,FALSE) -> 5500 | G5: =C5*0.4 -> 175.2 | H5: =D5*0.4 -> 0 | I5: =E5*0.4 -> 175.2 | K5: =IF(right(B5,2)="KG","TL","VS") -> VS
B6: GW-322 MAR-25-12-763-50 (CI) | C6: =sumif(Purchase!E$5:E1000,B6,Purchase!F$5:F1000) -> 409 | D6: =SUMIF(Sale!H:H,B6,Sale!I:I) -> 0 | E6: =C6-D6 -> 409 | F6: =VLOOKUP(B6,Table1[[Variety]:[Column1]],5,FALSE) -> 5500 | G6: =C6*0.4 -> 163.6 | H6: =D6*0.4 -> 0 | I6: =E6*0.4 -> 163.6 | K6: =IF(right(B6,2)="KG","TL","VS") -> VS
B7: GW-513 40KG | C7: =sumif(Purchase!E$5:E1000,B7,Purchase!F$5:F1000) -> 1641 | D7: =SUMIF(Sale!H:H,B7,Sale!I:I) -> 10 | E7: =C7-D7 -> 1631 | F7: =VLOOKUP(B7,Table1[[Variety]:[Column1]],5,FALSE) -> 5300 | G7: =C7*0.4 -> 656.4 | H7: =D7*0.4 -> 4 | I7: =E7*0.4 -> 652.4 | K7: =IF(right(B7,2)="KG","TL","VS") -> TL
B8: HD-4728(पूसा मालवी) MAR-25-12-763-38 (CI) | C8: =sumif(Purchase!E$5:E1000,B8,Purchase!F$5:F1000) -> 442 | D8: =SUMIF(Sale!H:H,B8,Sale!I:I) -> 0 | E8: =C8-D8 -> 442 | F8: =VLOOKUP(B8,Table1[[Variety]:[Column1]],5,FALSE) -> 5500 | G8: =C8*0.4 -> 176.8 | H8: =D8*0.4 -> 0 | I8: =E8*0.4 -> 176.8 | K8: =IF(right(B8,2)="KG","TL","VS") -> VS
B9: HD-4728(पूसा मालवी) MAR-25-12-763-37 (CI) | C9: =sumif(Purchase!E$5:E1000,B9,Purchase!F$5:F1000) -> 132 | D9: =SUMIF(Sale!H:H,B9,Sale!I:I) -> 0 | E9: =C9-D9 -> 132 | F9: =VLOOKUP(B9,Table1[[Variety]:[Column1]],5,FALSE) -> 5500 | G9: =C9*0.4 -> 52.8 | H9: =D9*0.4 -> 0 | I9: =E9*0.4 -> 52.8 | K9: =IF(right(B9,2)="KG","TL","VS") -> VS
B10: GW-322 40KG | C10: =sumif(Purchase!E$5:E1000,B10,Purchase!F$5:F1000) -> 76 | D10: =SUMIF(Sale!H:H,B10,Sale!I:I) -> 0 | E10: =C10-D10 -> 76 | F10: =VLOOKUP(B10,Table1[[Variety]:[Column1]],5,FALSE) -> 5300 | G10: =C10*0.4 -> 30.4 | H10: =D10*0.4 -> 0 | I10: =E10*0.4 -> 30.4 | K10: =IF(right(B10,2)="KG","TL","VS") -> TL
B11: LOK-1 MAR-25-12-763-13 (FI) | C11: =sumif(Purchase!E$5:E1000,B11,Purchase!F$5:F1000) -> 430 | D11: =SUMIF(Sale!H:H,B11,Sale!I:I) -> 0 | E11: =C11-D11 -> 430 | F11: =VLOOKUP(B11,Table1[[Variety]:[Column1]],5,FALSE) -> 5500 | G11: =C11*0.4 -> 172 | H11: =D11*0.4 -> 0 | I11: =E11*0.4 -> 172 | K11: =IF(right(B11,2)="KG","TL","VS") -> VS
B12: LOK-1 MAR-25-12-763-14 (FI) | C12: =sumif(Purchase!E$5:E1000,B12,Purchase!F$5:F1000) -> 171 | D12: =SUMIF(Sale!H:H,B12,Sale!I:I) -> 0 | E12: =C12-D12 -> 171 | F12: =VLOOKUP(B12,Table1[[Variety]:[Column1]],5,FALSE) -> 5500 | G12: =C12*0.4 -> 68.4 | H12: =D12*0.4 -> 0 | I12: =E12*0.4 -> 68.4 | K12: =IF(right(B12,2)="KG","TL","VS") -> VS
B13: LOK-1 MAR-25-12-763-19 (FI) | C13: =sumif(Purchase!E$5:E1000,B13,Purchase!F$5:F1000) -> 446 | D13: =SUMIF(Sale!H:H,B13,Sale!I:I) -> 0 | E13: =C13-D13 -> 446 | F13: =VLOOKUP(B13,Table1[[Variety]:[Column1]],5,FALSE) -> 5500 | G13: =C13*0.4 -> 178.4 | H13: =D13*0.4 -> 0 | I13: =E13*0.4 -> 178.4 | K13: =IF(right(B13,2)="KG","TL","VS") -> VS
B14: LOK-1 MAR-25-12-763-12 (FI) | C14: =sumif(Purchase!E$5:E1000,B14,Purchase!F$5:F1000) -> 200 | D14: =SUMIF(Sale!H:H,B14,Sale!I:I) -> 0 | E14: =C14-D14 -> 200 | F14: =VLOOKUP(B14,Table1[[Variety]:[Column1]],5,FALSE) -> 5500 | G14: =C14*0.4 -> 80 | H14: =D14*0.4 -> 0 | I14: =E14*0.4 -> 80 | K14: =IF(right(B14,2)="KG","TL","VS") -> VS
B15: HI-1650(पूसा ओजस्वी) MAR-25-12-763-40(3) (FII) | C15: =sumif(Purchase!E$5:E1000,B15,Purchase!F$5:F1000) -> 375 | D15: =SUMIF(Sale!H:H,B15,Sale!I:I) -> 0 | E15: =C15-D15 -> 375 | F15: =VLOOKUP(B15,Table1[[Variety]:[Column1]],5,FALSE) -> 5500 | G15: =C15*0.4 -> 150 | H15: =D15*0.4 -> 0 | I15: =E15*0.4 -> 150 | K15: =IF(right(B15,2)="KG","TL","VS") -> VS
B16: HI-1650(पूसा ओजस्वी) MAR-25-12-763-40 (FII) | C16: =sumif(Purchase!E$5:E1000,B16,Purchase!F$5:F1000) -> 342 | D16: =SUMIF(Sale!H:H,B16,Sale!I:I) -> 0 | E16: =C16-D16 -> 342 | F16: =VLOOKUP(B16,Table1[[Variety]:[Column1]],5,FALSE) -> 5500 | G16: =C16*0.4 -> 136.8 | H16: =D16*0.4 -> 0 | I16: =E16*0.4 -> 136.8 | K16: =IF(right(B16,2)="KG","TL","VS") -> VS
B17: HI-1650(पूसा ओजस्वी) MAR-25-12-763-40(2) (FII) | C17: =sumif(Purchase!E$5:E1000,B17,Purchase!F$5:F1000) -> 338 | D17: =SUMIF(Sale!H:H,B17,Sale!I:I) -> 0 | E17: =C17-D17 -> 338 | F17: =VLOOKUP(B17,Table1[[Variety]:[Column1]],5,FALSE) -> 5500 | G17: =C17*0.4 -> 135.2 | H17: =D17*0.4 -> 0 | I17: =E17*0.4 -> 135.2 | K17: =IF(right(B17,2)="KG","TL","VS") -> VS
B18: C-306 MAR-25-12-763-1 (FII) | C18: =sumif(Purchase!E$5:E1000,B18,Purchase!F$5:F1000) -> 340 | D18: =SUMIF(Sale!H:H,B18,Sale!I:I) -> 0 | E18: =C18-D18 -> 340 | F18: =VLOOKUP(B18,Table1[[Variety]:[Column1]],5,FALSE) -> 6500 | G18: =C18*0.4 -> 136 | H18: =D18*0.4 -> 0 | I18: =E18*0.4 -> 136 | K18: =IF(right(B18,2)="KG","TL","VS") -> VS
B19: C-306 40KG | C19: =sumif(Purchase!E$5:E1000,B19,Purchase!F$5:F1000) -> 877 | D19: =SUMIF(Sale!H:H,B19,Sale!I:I) -> 0 | E19: =C19-D19 -> 877 | F19: =VLOOKUP(B19,Table1[[Variety]:[Column1]],5,FALSE) -> 6000 | G19: =C19*0.4 -> 350.8 | H19: =D19*0.4 -> 0 | I19: =E19*0.4 -> 350.8 | K19: =IF(right(B19,2)="KG","TL","VS") -> TL
B20: HI-8713(पूसा मंगल) MAR-25-12-763-35 (FII) | C20: =sumif(Purchase!E$5:E1000,B20,Purchase!F$5:F1000) -> 433 | D20: =SUMIF(Sale!H:H,B20,Sale!I:I) -> 0 | E20: =C20-D20 -> 433 | F20: =VLOOKUP(B20,Table1[[Variety]:[Column1]],5,FALSE) -> 5500 | G20: =C20*0.4 -> 173.2 | H20: =D20*0.4 -> 0 | I20: =E20*0.4 -> 173.2 | K20: =IF(right(B20,2)="KG","TL","VS") -> VS
B21: HI-8713(पूसा मंगल) MAR-25-12-763-36(2) (FII) | C21: =sumif(Purchase!E$5:E1000,B21,Purchase!F$5:F1000) -> 212 | D21: =SUMIF(Sale!H:H,B21,Sale!I:I) -> 0 | E21: =C21-D21 -> 212 | F21: =VLOOKUP(B21,Table1[[Variety]:[Column1]],5,FALSE) -> 5500 | G21: =C21*0.4 -> 84.8 | H21: =D21*0.4 -> 0 | I21: =E21*0.4 -> 84.8 | K21: =IF(right(B21,2)="KG","TL","VS") -> VS
B22: 8826 40KG | C22: =sumif(Purchase!E$5:E1000,B22,Purchase!F$5:F1000) -> 354 | D22: =SUMIF(Sale!H:H,B22,Sale!I:I) -> 0 | E22: =C22-D22 -> 354 | F22: =VLOOKUP(B22,Table1[[Variety]:[Column1]],5,FALSE) -> 5000 | G22: =C22*0.4 -> 141.6 | H22: =D22*0.4 -> 0 | I22: =E22*0.4 -> 141.6 | K22: =IF(right(B22,2)="KG","TL","VS") -> TL
B23: HI-1655(पूसा हर्षा) 40KG | C23: =sumif(Purchase!E$5:E1000,B23,Purchase!F$5:F1000) -> 332 | D23: =SUMIF(Sale!H:H,B23,Sale!I:I) -> 10 | E23: =C23-D23 -> 322 | F23: =VLOOKUP(B23,Table1[[Variety]:[Column1]],5,FALSE) -> 5300 | G23: =C23*0.4 -> 132.8 | H23: =D23*0.4 -> 4 | I23: =E23*0.4 -> 128.8 | K23: =IF(right(B23,2)="KG","TL","VS") -> TL
B24: HI-1655(पूसा हर्षा) MAR-25-12-763-21 (FI) | C24: =sumif(Purchase!E$5:E1000,B24,Purchase!F$5:F1000) -> 130 | D24: =SUMIF(Sale!H:H,B24,Sale!I:I) -> 0 | E24: =C24-D24 -> 130 | F24: =VLOOKUP(B24,Table1[[Variety]:[Column1]],5,FALSE) -> 5500 | G24: =C24*0.4 -> 52 | H24: =D24*0.4 -> 0 | I24: =E24*0.4 -> 52 | K24: =IF(right(B24,2)="KG","TL","VS") -> VS
B25: HI-1650(पूसा ओजस्वी) 40KG | C25: =sumif(Purchase!E$5:E1000,B25,Purchase!F$5:F1000) -> 3891 | D25: =SUMIF(Sale!H:H,B25,Sale!I:I) -> 0 | E25: =C25-D25 -> 3891 | F25: =VLOOKUP(B25,Table1[[Variety]:[Column1]],5,FALSE) -> 5300 | G25: =C25*0.4 -> 1556.4 | H25: =D25*0.4 -> 0 | I25: =E25*0.4 -> 1556.4 | K25: =IF(right(B25,2)="KG","TL","VS") -> TL
B26: HI-1634(पूसा अहिल्या) 40KG | C26: =sumif(Purchase!E$5:E1000,B26,Purchase!F$5:F1000) -> 1272 | D26: =SUMIF(Sale!H:H,B26,Sale!I:I) -> 0 | E26: =C26-D26 -> 1272 | F26: =VLOOKUP(B26,Table1[[Variety]:[Column1]],5,FALSE) -> 5300 | G26: =C26*0.4 -> 508.8 | H26: =D26*0.4 -> 0 | I26: =E26*0.4 -> 508.8 | K26: =IF(right(B26,2)="KG","TL","VS") -> TL
B27: HD-3385 40KG | C27: =sumif(Purchase!E$5:E1000,B27,Purchase!F$5:F1000) -> 5431 | D27: =SUMIF(Sale!H:H,B27,Sale!I:I) -> 0 | E27: =C27-D27 -> 5431 | F27: =VLOOKUP(B27,Table1[[Variety]:[Column1]],5,FALSE) -> 5300 | G27: =C27*0.4 -> 2172.4 | H27: =D27*0.4 -> 0 | I27: =E27*0.4 -> 2172.4 | K27: =IF(right(B27,2)="KG","TL","VS") -> TL
B28: 33-88 40KG | C28: =sumif(Purchase!E$5:E1000,B28,Purchase!F$5:F1000) -> 259 | D28: =SUMIF(Sale!H:H,B28,Sale!I:I) -> 0 | E28: =C28-D28 -> 259 | F28: =VLOOKUP(B28,Table1[[Variety]:[Column1]],5,FALSE) -> 5000 | G28: =C28*0.4 -> 103.6 | H28: =D28*0.4 -> 0 | I28: =E28*0.4 -> 103.6 | K28: =IF(right(B28,2)="KG","TL","VS") -> TL
B29: 3390 40KG | C29: =sumif(Purchase!E$5:E1000,B29,Purchase!F$5:F1000) -> 564 | D29: =SUMIF(Sale!H:H,B29,Sale!I:I) -> 0 | E29: =C29-D29 -> 564 | F29: =VLOOKUP(B29,Table1[[Variety]:[Column1]],5,FALSE) -> 5000 | G29: =C29*0.4 -> 225.6 | H29: =D29*0.4 -> 0 | I29: =E29*0.4 -> 225.6 | K29: =IF(right(B29,2)="KG","TL","VS") -> TL
B30: HD-3410 40KG | C30: =sumif(Purchase!E$5:E1000,B30,Purchase!F$5:F1000) -> 784 | D30: =SUMIF(Sale!H:H,B30,Sale!I:I) -> 0 | E30: =C30-D30 -> 784 | F30: =VLOOKUP(B30,Table1[[Variety]:[Column1]],5,FALSE) -> 5300 | G30: =C30*0.4 -> 313.6 | H30: =D30*0.4 -> 0 | I30: =E30*0.4 -> 313.6 | K30: =IF(right(B30,2)="KG","TL","VS") -> TL
B31: HI-8830(पूसा किर्ति) 40KG | C31: =sumif(Purchase!E$5:E1000,B31,Purchase!F$5:F1000) -> 8257 | D31: =SUMIF(Sale!H:H,B31,Sale!I:I) -> 0 | E31: =C31-D31 -> 8257 | F31: =VLOOKUP(B31,Table1[[Variety]:[Column1]],5,FALSE) -> 5300 | G31: =C31*0.4 -> 3302.8 | H31: =D31*0.4 -> 0 | I31: =E31*0.4 -> 3302.8 | K31: =IF(right(B31,2)="KG","TL","VS") -> TL
B32: HD-3385 BR 40KG | C32: =sumif(Purchase!E$5:E1000,B32,Purchase!F$5:F1000) -> 259 | D32: =SUMIF(Sale!H:H,B32,Sale!I:I) -> 0 | E32: =C32-D32 -> 259 | F32: =VLOOKUP(B32,Table1[[Variety]:[Column1]],5,FALSE) -> 7000 | G32: =C32*0.4 -> 103.6 | H32: =D32*0.4 -> 0 | I32: =E32*0.4 -> 103.6 | K32: =IF(right(B32,2)="KG","TL","VS") -> TL
B33: LOK-1 40KG | C33: =sumif(Purchase!E$5:E1000,B33,Purchase!F$5:F1000) -> 688 | D33: =SUMIF(Sale!H:H,B33,Sale!I:I) -> 0 | E33: =C33-D33 -> 688 | F33: =VLOOKUP(B33,Table1[[Variety]:[Column1]],5,FALSE) -> 5300 | G33: =C33*0.4 -> 275.2 | H33: =D33*0.4 -> 0 | I33: =E33*0.4 -> 275.2 | K33: =IF(right(B33,2)="KG","TL","VS") -> TL
B34: PRADHAN(प्रधान) 40KG | C34: =sumif(Purchase!E$5:E1000,B34,Purchase!F$5:F1000) -> 945 | D34: =SUMIF(Sale!H:H,B34,Sale!I:I) -> 0 | E34: =C34-D34 -> 945 | F34: =VLOOKUP(B34,Table1[[Variety]:[Column1]],5,FALSE) -> 5000 | G34: =C34*0.4 -> 378 | H34: =D34*0.4 -> 0 | I34: =E34*0.4 -> 378 | K34: =IF(right(B34,2)="KG","TL","VS") -> TL
B35: MANAV(मानव) 40KG | C35: =sumif(Purchase!E$5:E1000,B35,Purchase!F$5:F1000) -> 199 | D35: =SUMIF(Sale!H:H,B35,Sale!I:I) -> 0 | E35: =C35-D35 -> 199 | F35: =VLOOKUP(B35,Table1[[Variety]:[Column1]],5,FALSE) -> 12000 | G35: =C35*0.4 -> 79.6 | H35: =D35*0.4 -> 0 | I35: =E35*0.4 -> 79.6 | K35: =IF(right(B35,2)="KG","TL","VS") -> TL
B36: SAMRUDDHI(समृद्धि) 40KG | C36: =sumif(Purchase!E$5:E1000,B36,Purchase!F$5:F1000) -> 127 | D36: =SUMIF(Sale!H:H,B36,Sale!I:I) -> 0 | E36: =C36-D36 -> 127 | F36: =VLOOKUP(B36,Table1[[Variety]:[Column1]],5,FALSE) -> 8000 | G36: =C36*0.4 -> 50.8 | H36: =D36*0.4 -> 0 | I36: =E36*0.4 -> 50.8 | K36: =IF(right(B36,2)="KG","TL","VS") -> TL
B37: HI-8759(पूसा तेजस) 40KG | C37: =sumif(Purchase!E$5:E1000,B37,Purchase!F$5:F1000) -> 8615 | D37: =SUMIF(Sale!H:H,B37,Sale!I:I) -> 0 | E37: =C37-D37 -> 8615 | F37: =VLOOKUP(B37,Table1[[Variety]:[Column1]],5,FALSE) -> 5300 | G37: =C37*0.4 -> 3446 | H37: =D37*0.4 -> 0 | I37: =E37*0.4 -> 3446 | K37: =IF(right(B37,2)="KG","TL","VS") -> TL
B38: HI-8713(पूसा मंगल) MAR-25-12-763-36 (FII) | C38: =sumif(Purchase!E$5:E1000,B38,Purchase!F$5:F1000) -> 417 | D38: =SUMIF(Sale!H:H,B38,Sale!I:I) -> 0 | E38: =C38-D38 -> 417 | F38: =VLOOKUP(B38,Table1[[Variety]:[Column1]],5,FALSE) -> 5500 | G38: =C38*0.4 -> 166.8 | H38: =D38*0.4 -> 0 | I38: =E38*0.4 -> 166.8 | K38: =IF(right(B38,2)="KG","TL","VS") -> VS
B39: HI-8759(पूसा तेजस) MAR-25-12-763-52 (FII) | C39: =sumif(Purchase!E$5:E1000,B39,Purchase!F$5:F1000) -> 435 | D39: =SUMIF(Sale!H:H,B39,Sale!I:I) -> 0 | E39: =C39-D39 -> 435 | F39: =VLOOKUP(B39,Table1[[Variety]:[Column1]],5,FALSE) -> 5500 | G39: =C39*0.4 -> 174 | H39: =D39*0.4 -> 0 | I39: =E39*0.4 -> 174 | K39: =IF(right(B39,2)="KG","TL","VS") -> VS
B40: HI-8759(पूसा तेजस) MAR-25-12-763-51 (FII) | C40: =sumif(Purchase!E$5:E1000,B40,Purchase!F$5:F1000) -> 441 | D40: =SUMIF(Sale!H:H,B40,Sale!I:I) -> 0 | E40: =C40-D40 -> 441 | F40: =VLOOKUP(B40,Table1[[Variety]:[Column1]],5,FALSE) -> 5500 | G40: =C40*0.4 -> 176.4 | H40: =D40*0.4 -> 0 | I40: =E40*0.4 -> 176.4 | K40: =IF(right(B40,2)="KG","TL","VS") -> VS
B41: HI-8759(पूसा तेजस) MAR-25-12-763-52(2) (FII) | C41: =sumif(Purchase!E$5:E1000,B41,Purchase!F$5:F1000) -> 618 | D41: =SUMIF(Sale!H:H,B41,Sale!I:I) -> 0 | E41: =C41-D41 -> 618 | F41: =VLOOKUP(B41,Table1[[Variety]:[Column1]],5,FALSE) -> 5500 | G41: =C41*0.4 -> 247.2 | H41: =D41*0.4 -> 0 | I41: =E41*0.4 -> 247.2 | K41: =IF(right(B41,2)="KG","TL","VS") -> VS
B42: HI-8830(पूसा किर्ति) APR-25-12-763-28 (FII) | C42: =sumif(Purchase!E$5:E1000,B42,Purchase!F$5:F1000) -> 300 | D42: =SUMIF(Sale!H:H,B42,Sale!I:I) -> 0 | E42: =C42-D42 -> 300 | F42: =VLOOKUP(B42,Table1[[Variety]:[Column1]],5,FALSE) -> 5500 | G42: =C42*0.4 -> 120 | H42: =D42*0.4 -> 0 | I42: =E42*0.4 -> 120 | K42: =IF(right(B42,2)="KG","TL","VS") -> VS
B43: HI-8830(पूसा किर्ति) APR-25-12-763-28(2) (FII) | C43: =sumif(Purchase!E$5:E1000,B43,Purchase!F$5:F1000) -> 115 | D43: =SUMIF(Sale!H:H,B43,Sale!I:I) -> 0 | E43: =C43-D43 -> 115 | F43: =VLOOKUP(B43,Table1[[Variety]:[Column1]],5,FALSE) -> 5500 | G43: =C43*0.4 -> 46 | H43: =D43*0.4 -> 0 | I43: =E43*0.4 -> 46 | K43: =IF(right(B43,2)="KG","TL","VS") -> VS
B44: HI-8830(पूसा किर्ति) MAR-25-12-763-27(2) (FII) | C44: =sumif(Purchase!E$5:E1000,B44,Purchase!F$5:F1000) -> 233 | D44: =SUMIF(Sale!H:H,B44,Sale!I:I) -> 0 | E44: =C44-D44 -> 233 | F44: =VLOOKUP(B44,Table1[[Variety]:[Column1]],5,FALSE) -> 5500 | G44: =C44*0.4 -> 93.2 | H44: =D44*0.4 -> 0 | I44: =E44*0.4 -> 93.2 | K44: =IF(right(B44,2)="KG","TL","VS") -> VS
B45: HI-1634(पूसा अहिल्या) MAR-25-12-763-48 (FII) | C45: =sumif(Purchase!E$5:E1000,B45,Purchase!F$5:F1000) -> 252 | D45: =SUMIF(Sale!H:H,B45,Sale!I:I) -> 0 | E45: =C45-D45 -> 252 | F45: =VLOOKUP(B45,Table1[[Variety]:[Column1]],5,FALSE) -> 5500 | G45: =C45*0.4 -> 100.8 | H45: =D45*0.4 -> 0 | I45: =E45*0.4 -> 100.8 | K45: =IF(right(B45,2)="KG","TL","VS") -> VS
B46: HI-8830(पूसा किर्ति) MAR-25-12-763-27 (FII) | C46: =sumif(Purchase!E$5:E1000,B46,Purchase!F$5:F1000) -> 439 | D46: =SUMIF(Sale!H:H,B46,Sale!I:I) -> 0 | E46: =C46-D46 -> 439 | F46: =VLOOKUP(B46,Table1[[Variety]:[Column1]],5,FALSE) -> 5500 | G46: =C46*0.4 -> 175.6 | H46: =D46*0.4 -> 0 | I46: =E46*0.4 -> 175.6 | K46: =IF(right(B46,2)="KG","TL","VS") -> VS
B47: HI-8713(पूसा मंगल) 40KG | C47: =sumif(Purchase!E$5:E1000,B47,Purchase!F$5:F1000) -> 3710 | D47: =SUMIF(Sale!H:H,B47,Sale!I:I) -> 0 | E47: =C47-D47 -> 3710 | F47: =VLOOKUP(B47,Table1[[Variety]:[Column1]],5,FALSE) -> 5300 | G47: =C47*0.4 -> 1484 | H47: =D47*0.4 -> 0 | I47: =E47*0.4 -> 1484 | K47: =IF(right(B47,2)="KG","TL","VS") -> TL
B48: DAFTARI 21 10KG | C48: =sumif(Purchase!E$5:E1000,B48,Purchase!F$5:F1000) -> 300 | D48: =SUMIF(Sale!H:H,B48,Sale!I:I) -> 0 | E48: =C48-D48 -> 300 | F48: =VLOOKUP(B48,Table1[[Variety]:[Column1]],5,FALSE) -> 14000 | G48: =C48*0.4 -> 120 | H48: =D48*0.4 -> 0 | I48: =E48*0.4 -> 120 | K48: =IF(right(B48,2)="KG","TL","VS") -> TL
B49: LOK-1 MAR-25-12-763-18 (FI) | C49: =sumif(Purchase!E$5:E1000,B49,Purchase!F$5:F1000) -> 206 | D49: =SUMIF(Sale!H:H,B49,Sale!I:I) -> 0 | E49: =C49-D49 -> 206 | F49: =VLOOKUP(B49,Table1[[Variety]:[Column1]],5,FALSE) | G49: =C49*0.4 -> 82.4 | H49: =D49*0.4 -> 0 | I49: =E49*0.4 -> 82.4 | K49: =IF(right(B49,2)="KG","TL","VS") -> VS
B50: HI-1544 (पूर्णा) 40KG | C50: =sumif(Purchase!E$5:E1000,B50,Purchase!F$5:F1000) -> 564 | D50: =SUMIF(Sale!H:H,B50,Sale!I:I) -> 0 | E50: =C50-D50 -> 564 | F50: =VLOOKUP(B50,Table1[[Variety]:[Column1]],5,FALSE) -> 5300 | G50: =C50*0.4 -> 225.6 | H50: =D50*0.4 -> 0 | I50: =E50*0.4 -> 225.6 | K50: =IF(right(B50,2)="KG","TL","VS") -> TL
B51: HI-8830(पूसा किर्ति) APR-25-12-763-31 (FII) | C51: =sumif(Purchase!E$5:E1000,B51,Purchase!F$5:F1000) -> 437 | D51: =SUMIF(Sale!H:H,B51,Sale!I:I) -> 0 | E51: =C51-D51 -> 437 | F51: =VLOOKUP(B51,Table1[[Variety]:[Column1]],5,FALSE) -> 5500 | G51: =C51*0.4 -> 174.8 | H51: =D51*0.4 -> 0 | I51: =E51*0.4 -> 174.8 | K51: =IF(right(B51,2)="KG","TL","VS") -> VS
B52: HI-1650(पूसा ओजस्वी) MAR-25-12-763-43 (FII) | C52: =sumif(Purchase!E$5:E1000,B52,Purchase!F$5:F1000) -> 300 | D52: =SUMIF(Sale!H:H,B52,Sale!I:I) -> 0 | E52: =C52-D52 -> 300 | F52: =VLOOKUP(B52,Table1[[Variety]:[Column1]],5,FALSE) -> 5500 | G52: =C52*0.4 -> 120 | H52: =D52*0.4 -> 0 | I52: =E52*0.4 -> 120 | K52: =IF(right(B52,2)="KG","TL","VS") -> VS
B53: 16-69 40KG | C53: =sumif(Purchase!E$5:E1000,B53,Purchase!F$5:F1000) -> 162 | D53: =SUMIF(Sale!H:H,B53,Sale!I:I) -> 0 | E53: =C53-D53 -> 162 | F53: =VLOOKUP(B53,Table1[[Variety]:[Column1]],5,FALSE) -> 8000 | G53: =C53*0.4 -> 64.8 | H53: =D53*0.4 -> 0 | I53: =E53*0.4 -> 64.8 | K53: =IF(right(B53,2)="KG","TL","VS") -> TL
B54: LOK-1 MAR-25-12-763-8 (FI) | C54: =sumif(Purchase!E$5:E1000,B54,Purchase!F$5:F1000) -> 244 | D54: =SUMIF(Sale!H:H,B54,Sale!I:I) -> 0 | E54: =C54-D54 -> 244 | F54: =VLOOKUP(B54,Table1[[Variety]:[Column1]],5,FALSE) -> 5500 | G54: =C54*0.4 -> 97.6 | H54: =D54*0.4 -> 0 | I54: =E54*0.4 -> 97.6 | K54: =IF(right(B54,2)="KG","TL","VS") -> VS
B55: HI-8759(पूसा तेजस) MAR-25-12-763-54(2) (FII) | C55: =sumif(Purchase!E$5:E1000,B55,Purchase!F$5:F1000) -> 140 | D55: =SUMIF(Sale!H:H,B55,Sale!I:I) -> 0 | E55: =C55-D55 -> 140 | F55: =VLOOKUP(B55,Table1[[Variety]:[Column1]],5,FALSE) -> 5500 | G55: =C55*0.4 -> 56 | H55: =D55*0.4 -> 0 | I55: =E55*0.4 -> 56 | K55: =IF(right(B55,2)="KG","TL","VS") -> VS
B56: HI-8759(पूसा तेजस) MAR-25-12-763-54 (FII) | C56: =sumif(Purchase!E$5:E1000,B56,Purchase!F$5:F1000) -> 438 | D56: =SUMIF(Sale!H:H,B56,Sale!I:I) -> 0 | E56: =C56-D56 -> 438 | F56: =VLOOKUP(B56,Table1[[Variety]:[Column1]],5,FALSE) -> 5500 | G56: =C56*0.4 -> 175.2 | H56: =D56*0.4 -> 0 | I56: =E56*0.4 -> 175.2 | K56: =IF(right(B56,2)="KG","TL","VS") -> VS
B57: HI-8713(पूसा मंगल) MAR-25-12-763-35(2) (FII) | C57: =sumif(Purchase!E$5:E1000,B57,Purchase!F$5:F1000) -> 107 | D57: =SUMIF(Sale!H:H,B57,Sale!I:I) -> 0 | E57: =C57-D57 -> 107 | F57: =VLOOKUP(B57,Table1[[Variety]:[Column1]],5,FALSE) -> 5500 | G57: =C57*0.4 -> 42.8 | H57: =D57*0.4 -> 0 | I57: =E57*0.4 -> 42.8 | K57: =IF(right(B57,2)="KG","TL","VS") -> VS
B58: LOK-1 APR-25-12-763-9(2) (FI) | C58: =sumif(Purchase!E$5:E1000,B58,Purchase!F$5:F1000) -> 353 | D58: =SUMIF(Sale!H:H,B58,Sale!I:I) -> 0 | E58: =C58-D58 -> 353 | F58: =VLOOKUP(B58,Table1[[Variety]:[Column1]],5,FALSE) -> 5500 | G58: =C58*0.4 -> 141.2 | H58: =D58*0.4 -> 0 | I58: =E58*0.4 -> 141.2 | K58: =IF(right(B58,2)="KG","TL","VS") -> VS
B59: HI-8830(पूसा किर्ति) APR-25-12-763-26 (FII) | C59: =sumif(Purchase!E$5:E1000,B59,Purchase!F$5:F1000) -> 437 | D59: =SUMIF(Sale!H:H,B59,Sale!I:I) -> 0 | E59: =C59-D59 -> 437 | F59: =VLOOKUP(B59,Table1[[Variety]:[Column1]],5,FALSE) -> 5500 | G59: =C59*0.4 -> 174.8 | H59: =D59*0.4 -> 0 | I59: =E59*0.4 -> 174.8 | K59: =IF(right(B59,2)="KG","TL","VS") -> VS
B60: HI-1650(पूसा ओजस्वी) APR-25-12-763-40(2) (FII) | C60: =sumif(Purchase!E$5:E1000,B60,Purchase!F$5:F1000) -> 108 | D60: =SUMIF(Sale!H:H,B60,Sale!I:I) -> 0 | E60: =C60-D60 -> 108 | F60: =VLOOKUP(B60,Table1[[Variety]:[Column1]],5,FALSE) -> 5500 | G60: =C60*0.4 -> 43.2 | H60: =D60*0.4 -> 0 | I60: =E60*0.4 -> 43.2 | K60: =IF(right(B60,2)="KG","TL","VS") -> VS
B61: HI-8830(पूसा किर्ति) APR-25-12-763-29(2) (FII) | C61: =sumif(Purchase!E$5:E1000,B61,Purchase!F$5:F1000) -> 368 | D61: =SUMIF(Sale!H:H,B61,Sale!I:I) -> 0 | E61: =C61-D61 -> 368 | F61: =VLOOKUP(B61,Table1[[Variety]:[Column1]],5,FALSE) -> 5500 | G61: =C61*0.4 -> 147.2 | H61: =D61*0.4 -> 0 | I61: =E61*0.4 -> 147.2
B62: HI-8830(पूसा किर्ति) APR-25-12-763-29 (FII) | C62: =sumif(Purchase!E$5:E1000,B62,Purchase!F$5:F1000) -> 449 | D62: =SUMIF(Sale!H:H,B62,Sale!I:I) -> 0 | E62: =C62-D62 -> 449 | F62: =VLOOKUP(B62,Table1[[Variety]:[Column1]],5,FALSE) -> 5500 | G62: =C62*0.4 -> 179.6 | H62: =D62*0.4 -> 0 | I62: =E62*0.4 -> 179.6
B63: LOK-1 APR-25-12-763-4 (FI) | C63: =sumif(Purchase!E$5:E1000,B63,Purchase!F$5:F1000) -> 150 | D63: =SUMIF(Sale!H:H,B63,Sale!I:I) -> 0 | E63: =C63-D63 -> 150 | F63: =VLOOKUP(B63,Table1[[Variety]:[Column1]],5,FALSE) -> 5500 | G63: =C63*0.4 -> 60 | H63: =D63*0.4 -> 0 | I63: =E63*0.4 -> 60
B64: SHREEAM SR-14 40KG | C64: =sumif(Purchase!E$5:E1000,B64,Purchase!F$5:F1000) -> 50 | D64: =SUMIF(Sale!H:H,B64,Sale!I:I) -> 0 | E64: =C64-D64 -> 50 | F64: =VLOOKUP(B64,Table1[[Variety]:[Column1]],5,FALSE) -> 9000 | G64: =C64*0.4 -> 20 | H64: =D64*0.4 -> 0 | I64: =E64*0.4 -> 20
B65: SHREERAM SUPER 303 40KG | C65: =sumif(Purchase!E$5:E1000,B65,Purchase!F$5:F1000) -> 385 | D65: =SUMIF(Sale!H:H,B65,Sale!I:I) -> 0 | E65: =C65-D65 -> 385 | F65: =VLOOKUP(B65,Table1[[Variety]:[Column1]],5,FALSE) -> 8500 | G65: =C65*0.4 -> 154 | H65: =D65*0.4 -> 0 | I65: =E65*0.4 -> 154
B66: HI-8759(पूसा तेजस) MAR-25-12-763-53 (FII) | C66: =sumif(Purchase!E$5:E1000,B66,Purchase!F$5:F1000) -> 336 | D66: =SUMIF(Sale!H:H,B66,Sale!I:I) -> 0 | E66: =C66-D66 -> 336 | F66: =VLOOKUP(B66,Table1[[Variety]:[Column1]],5,FALSE) -> 5500 | G66: =C66*0.4 -> 134.4 | H66: =D66*0.4 -> 0 | I66: =E66*0.4 -> 134.4
B67: HI-8830(पूसा किर्ति) APR-25-12-763-33 (FII) | C67: =sumif(Purchase!E$5:E1000,B67,Purchase!F$5:F1000) -> 349 | D67: =SUMIF(Sale!H:H,B67,Sale!I:I) -> 0 | E67: =C67-D67 -> 349 | F67: =VLOOKUP(B67,Table1[[Variety]:[Column1]],5,FALSE) -> 5500 | G67: =C67*0.4 -> 139.6 | H67: =D67*0.4 -> 0 | I67: =E67*0.4 -> 139.6
B68: HI-8830(पूसा किर्ति) APR-25-12-763-30(2) (FII) | C68: =sumif(Purchase!E$5:E1000,B68,Purchase!F$5:F1000) -> 229 | D68: =SUMIF(Sale!H:H,B68,Sale!I:I) -> 0 | E68: =C68-D68 -> 229 | F68: =VLOOKUP(B68,Table1[[Variety]:[Column1]],5,FALSE) -> 5500 | G68: =C68*0.4 -> 91.6 | H68: =D68*0.4 -> 0 | I68: =E68*0.4 -> 91.6
B69: HI-1650(पूसा ओजस्वी) APR-25-12-763-42 (FII) | C69: =sumif(Purchase!E$5:E1000,B69,Purchase!F$5:F1000) -> 450 | D69: =SUMIF(Sale!H:H,B69,Sale!I:I) -> 0 | E69: =C69-D69 -> 450 | F69: =VLOOKUP(B69,Table1[[Variety]:[Column1]],5,FALSE) -> 5500 | G69: =C69*0.4 -> 180 | H69: =D69*0.4 -> 0 | I69: =E69*0.4 -> 180
B70: HI-8830(पूसा किर्ति) APR-25-12-763-22(3) (FII) | C70: =sumif(Purchase!E$5:E1000,B70,Purchase!F$5:F1000) -> 114 | D70: =SUMIF(Sale!H:H,B70,Sale!I:I) -> 0 | E70: =C70-D70 -> 114 | F70: =VLOOKUP(B70,Table1[[Variety]:[Column1]],5,FALSE) -> 5500 | G70: =C70*0.4 -> 45.6 | H70: =D70*0.4 -> 0 | I70: =E70*0.4 -> 45.6
B71: HI-8830(पूसा किर्ति) APR-25-12-763-22 (FII) | C71: =sumif(Purchase!E$5:E1000,B71,Purchase!F$5:F1000) -> 445 | D71: =SUMIF(Sale!H:H,B71,Sale!I:I) -> 0 | E71: =C71-D71 -> 445 | F71: =VLOOKUP(B71,Table1[[Variety]:[Column1]],5,FALSE) -> 5500 | G71: =C71*0.4 -> 178 | H71: =D71*0.4 -> 0 | I71: =E71*0.4 -> 178
B72: HI-1650(पूसा ओजस्वी) MAR25-12-763-39 (FI) | C72: =sumif(Purchase!E$5:E1000,B72,Purchase!F$5:F1000) -> 109 | D72: =SUMIF(Sale!H:H,B72,Sale!I:I) -> 0 | E72: =C72-D72 -> 109 | F72: =VLOOKUP(B72,Table1[[Variety]:[Column1]],5,FALSE) -> 7500 | G72: =C72*0.4 -> 43.6 | H72: =D72*0.4 -> 0 | I72: =E72*0.4 -> 43.6
B73: HI-1650(पूसा ओजस्वी) APR-25-12-763-46 (FII) | C73: =sumif(Purchase!E$5:E1000,B73,Purchase!F$5:F1000) -> 450 | D73: =SUMIF(Sale!H:H,B73,Sale!I:I) -> 0 | E73: =C73-D73 -> 450 | F73: =VLOOKUP(B73,Table1[[Variety]:[Column1]],5,FALSE) -> 5500 | G73: =C73*0.4 -> 180 | H73: =D73*0.4 -> 0 | I73: =E73*0.4 -> 180
B74: HI-8830(पूसा किर्ति) APR-25-12-763-30 (FII) | C74: =sumif(Purchase!E$5:E1000,B74,Purchase!F$5:F1000) -> 438 | D74: =SUMIF(Sale!H:H,B74,Sale!I:I) -> 0 | E74: =C74-D74 -> 438 | F74: =VLOOKUP(B74,Table1[[Variety]:[Column1]],5,FALSE) -> 5500 | G74: =C74*0.4 -> 175.2 | H74: =D74*0.4 -> 0 | I74: =E74*0.4 -> 175.2
B75: MANAV(मानव) 50KG | C75: =sumif(Purchase!E$5:E1000,B75,Purchase!F$5:F1000) -> 62 | D75: =SUMIF(Sale!H:H,B75,Sale!I:I) -> 0 | E75: =C75-D75 -> 62 | F75: =VLOOKUP(B75,Table1[[Variety]:[Column1]],5,FALSE) -> 9000 | G75: =C75*0.4 -> 24.8 | H75: =D75*0.4 -> 0 | I75: =E75*0.4 -> 24.8
B76: LOK-1 APR-25-12-763-4(2) (FI) | C76: =sumif(Purchase!E$5:E1000,B76,Purchase!F$5:F1000) -> 115 | D76: =SUMIF(Sale!H:H,B76,Sale!I:I) -> 0 | E76: =C76-D76 -> 115 | F76: =VLOOKUP(B76,Table1[[Variety]:[Column1]],5,FALSE) -> 5500 | G76: =C76*0.4 -> 46 | H76: =D76*0.4 -> 0 | I76: =E76*0.4 -> 46
B77: LOK-1 APR-25-12-763-7 (FI) | C77: =sumif(Purchase!E$5:E1000,B77,Purchase!F$5:F1000) -> 333 | D77: =SUMIF(Sale!H:H,B77,Sale!I:I) -> 0 | E77: =C77-D77 -> 333 | F77: =VLOOKUP(B77,Table1[[Variety]:[Column1]],5,FALSE) -> 5500 | G77: =C77*0.4 -> 133.2 | H77: =D77*0.4 -> 0 | I77: =E77*0.4 -> 133.2
B78: HI-8830(पूसा किर्ति) APR-25-12-763-24(2) (FII) | C78: =sumif(Purchase!E$5:E1000,B78,Purchase!F$5:F1000) -> 470 | D78: =SUMIF(Sale!H:H,B78,Sale!I:I) -> 0 | E78: =C78-D78 -> 470 | F78: =VLOOKUP(B78,Table1[[Variety]:[Column1]],5,FALSE) -> 5500 | G78: =C78*0.4 -> 188 | H78: =D78*0.4 -> 0 | I78: =E78*0.4 -> 188
B79: LOK-1 APR-25-12-763-17 (FI) | C79: =sumif(Purchase!E$5:E1000,B79,Purchase!F$5:F1000) -> 300 | D79: =SUMIF(Sale!H:H,B79,Sale!I:I) -> 0 | E79: =C79-D79 -> 300 | F79: =VLOOKUP(B79,Table1[[Variety]:[Column1]],5,FALSE) -> 5500 | G79: =C79*0.4 -> 120 | H79: =D79*0.4 -> 0 | I79: =E79*0.4 -> 120
B80: HI-1650(पूसा ओजस्वी) APR-25-12-763-44(2) (FII) | C80: =sumif(Purchase!E$5:E1000,B80,Purchase!F$5:F1000) -> 194 | D80: =SUMIF(Sale!H:H,B80,Sale!I:I) -> 0 | E80: =C80-D80 -> 194 | F80: =VLOOKUP(B80,Table1[[Variety]:[Column1]],5,FALSE) -> 5500 | G80: =C80*0.4 -> 77.6 | H80: =D80*0.4 -> 0 | I80: =E80*0.4 -> 77.6
B81: HI-1650(पूसा ओजस्वी) APR-25-12-763-43 (FII) | C81: =sumif(Purchase!E$5:E1000,B81,Purchase!F$5:F1000) -> 420 | D81: =SUMIF(Sale!H:H,B81,Sale!I:I) -> 0 | E81: =C81-D81 -> 420 | F81: =VLOOKUP(B81,Table1[[Variety]:[Column1]],5,FALSE) -> 5500 | G81: =C81*0.4 -> 168 | H81: =D81*0.4 -> 0 | I81: =E81*0.4 -> 168
B82: HI-8830(पूसा किर्ति) APR-25-12-763-24 (FII) | C82: =sumif(Purchase!E$5:E1000,B82,Purchase!F$5:F1000) -> 414 | D82: =SUMIF(Sale!H:H,B82,Sale!I:I) -> 0 | E82: =C82-D82 -> 414 | F82: =VLOOKUP(B82,Table1[[Variety]:[Column1]],5,FALSE) -> 5500 | G82: =C82*0.4 -> 165.6 | H82: =D82*0.4 -> 0 | I82: =E82*0.4 -> 165.6
B83: SHREERAM SUPER 5-SR-05 40KG | C83: =sumif(Purchase!E$5:E1000,B83,Purchase!F$5:F1000) -> 75 | D83: =SUMIF(Sale!H:H,B83,Sale!I:I) -> 0 | E83: =C83-D83 -> 75 | F83: =VLOOKUP(B83,Table1[[Variety]:[Column1]],5,FALSE) -> 8500 | G83: =C83*0.4 -> 30 | H83: =D83*0.4 -> 0 | I83: =E83*0.4 -> 30
B84: HI-8830(पूसा किर्ति) MAR25-12-763-34 (FI) | C84: =sumif(Purchase!E$5:E1000,B84,Purchase!F$5:F1000) -> 252 | D84: =SUMIF(Sale!H:H,B84,Sale!I:I) -> 0 | E84: =C84-D84 -> 252 | F84: =VLOOKUP(B84,Table1[[Variety]:[Column1]],5,FALSE) -> 7500 | G84: =C84*0.4 -> 100.8 | H84: =D84*0.4 -> 0 | I84: =E84*0.4 -> 100.8
B85: HI-1650(पूसा ओजस्वी) APR-25-12-763-45 (FII) | C85: =sumif(Purchase!E$5:E1000,B85,Purchase!F$5:F1000) -> 468 | D85: =SUMIF(Sale!H:H,B85,Sale!I:I) -> 0 | E85: =C85-D85 -> 468 | F85: =VLOOKUP(B85,Table1[[Variety]:[Column1]],5,FALSE) -> 5500 | G85: =C85*0.4 -> 187.2 | H85: =D85*0.4 -> 0 | I85: =E85*0.4 -> 187.2
B86: JKG 5 KABULI 50KG | C86: =sumif(Purchase!E$5:E1000,B86,Purchase!F$5:F1000) -> 60 | D86: =SUMIF(Sale!H:H,B86,Sale!I:I) -> 0 | E86: =C86-D86 -> 60 | F86: =VLOOKUP(B86,Table1[[Variety]:[Column1]],5,FALSE) -> 12000 | G86: =C86*0.4 -> 24 | H86: =D86*0.4 -> 0 | I86: =E86*0.4 -> 24
B87: HI-8759(पूसा तेजस) (D) | C87: =sumif(Purchase!E$5:E1000,B87,Purchase!F$5:F1000) -> 297 | D87: =SUMIF(Sale!H:H,B87,Sale!I:I) -> 0 | E87: =C87-D87 -> 297 | F87: =VLOOKUP(B87,Table1[[Variety]:[Column1]],5,FALSE) -> 5300 | G87: =C87*0.4 -> 118.8 | H87: =D87*0.4 -> 0 | I87: =E87*0.4 -> 118.8
B88: HI-8830(पूसा किर्ति) APR-25-12-763-23(2) (FII) | C88: =sumif(Purchase!E$5:E1000,B88,Purchase!F$5:F1000) -> 400 | D88: =SUMIF(Sale!H:H,B88,Sale!I:I) -> 0 | E88: =C88-D88 -> 400 | F88: =VLOOKUP(B88,Table1[[Variety]:[Column1]],5,FALSE) -> 5500 | G88: =C88*0.4 -> 160 | H88: =D88*0.4 -> 0 | I88: =E88*0.4 -> 160
B89: HI-8830(पूसा किर्ति) APR-25-12-763-32 (FII) | C89: =sumif(Purchase!E$5:E1000,B89,Purchase!F$5:F1000) -> 250 | D89: =SUMIF(Sale!H:H,B89,Sale!I:I) -> 0 | E89: =C89-D89 -> 250 | F89: =VLOOKUP(B89,Table1[[Variety]:[Column1]],5,FALSE) -> 5500 | G89: =C89*0.4 -> 100 | H89: =D89*0.4 -> 0 | I89: =E89*0.4 -> 100
B90: LOK-1 APR-25-12-763-16 (FI) | C90: =sumif(Purchase!E$5:E1000,B90,Purchase!F$5:F1000) -> 150 | D90: =SUMIF(Sale!H:H,B90,Sale!I:I) -> 0 | E90: =C90-D90 -> 150 | F90: =VLOOKUP(B90,Table1[[Variety]:[Column1]],5,FALSE) -> 5500 | G90: =C90*0.4 -> 60 | H90: =D90*0.4 -> 0 | I90: =E90*0.4 -> 60
B91: HI-8830(पूसा किर्ति) APR-25-12-763-25(2) (FII) | C91: =sumif(Purchase!E$5:E1000,B91,Purchase!F$5:F1000) -> 260 | D91: =SUMIF(Sale!H:H,B91,Sale!I:I) -> 0 | E91: =C91-D91 -> 260 | F91: =VLOOKUP(B91,Table1[[Variety]:[Column1]],5,FALSE) -> 5500 | G91: =C91*0.4 -> 104 | H91: =D91*0.4 -> 0 | I91: =E91*0.4 -> 104
B92: HI-8830(पूसा किर्ति) APR-25-12-763-25 (FII) | C92: =sumif(Purchase!E$5:E1000,B92,Purchase!F$5:F1000) -> 440 | D92: =SUMIF(Sale!H:H,B92,Sale!I:I) -> 0 | E92: =C92-D92 -> 440 | F92: =VLOOKUP(B92,Table1[[Variety]:[Column1]],5,FALSE) -> 5500 | G92: =C92*0.4 -> 176 | H92: =D92*0.4 -> 0 | I92: =E92*0.4 -> 176
B93: LOK-1 APR-25-12-763-2(2) (FI) | C93: =sumif(Purchase!E$5:E1000,B93,Purchase!F$5:F1000) -> 72 | D93: =SUMIF(Sale!H:H,B93,Sale!I:I) -> 0 | E93: =C93-D93 -> 72 | F93: =VLOOKUP(B93,Table1[[Variety]:[Column1]],5,FALSE) -> 5500 | G93: =C93*0.4 -> 28.8 | H93: =D93*0.4 -> 0 | I93: =E93*0.4 -> 28.8
B94: LOK-1 APR-25-12-763-5 (FI) | C94: =sumif(Purchase!E$5:E1000,B94,Purchase!F$5:F1000) -> 78 | D94: =SUMIF(Sale!H:H,B94,Sale!I:I) -> 0 | E94: =C94-D94 -> 78 | F94: =VLOOKUP(B94,Table1[[Variety]:[Column1]],5,FALSE) -> 5500 | G94: =C94*0.4 -> 31.2 | H94: =D94*0.4 -> 0 | I94: =E94*0.4 -> 31.2
B95: HI-8830(पूसा किर्ति) APR-2024-12-763-135637-FI-A | C95: =sumif(Purchase!E$5:E1000,B95,Purchase!F$5:F1000) -> 0 | D95: =SUMIF(Sale!H:H,B95,Sale!I:I) -> 0 | E95: =C95-D95 -> 0 | F95: =VLOOKUP(B95,Table1[[Variety]:[Column1]],5,FALSE) -> 7500 | G95: =C95*0.4 -> 0 | H95: =D95*0.4 -> 0 | I95: =E95*0.4 -> 0
B96: HI-8830(पूसा किर्ति) APR-2024-12-763-135641-FI-I-C | C96: =sumif(Purchase!E$5:E1000,B96,Purchase!F$5:F1000) -> 0 | D96: =SUMIF(Sale!H:H,B96,Sale!I:I) -> 0 | E96: =C96-D96 -> 0 | F96: =VLOOKUP(B96,Table1[[Variety]:[Column1]],5,FALSE) -> 7500 | G96: =C96*0.4 -> 0 | H96: =D96*0.4 -> 0 | I96: =E96*0.4 -> 0
B97: HI-8830(पूसा किर्ति) APR-2024-12-763-135635-FI-A | C97: =sumif(Purchase!E$5:E1000,B97,Purchase!F$5:F1000) -> 0 | D97: =SUMIF(Sale!H:H,B97,Sale!I:I) -> 0 | E97: =C97-D97 -> 0 | F97: =VLOOKUP(B97,Table1[[Variety]:[Column1]],5,FALSE) -> 7500 | G97: =C97*0.4 -> 0 | H97: =D97*0.4 -> 0 | I97: =E97*0.4 -> 0
B98: HI-8830(पूसा किर्ति) APR-2024-12-763-135641-FI-II-A | C98: =sumif(Purchase!E$5:E1000,B98,Purchase!F$5:F1000) -> 363 | D98: =SUMIF(Sale!H:H,B98,Sale!I:I) -> 0 | E98: =C98-D98 -> 363 | F98: =VLOOKUP(B98,Table1[[Variety]:[Column1]],5,FALSE) -> 7500 | G98: =C98*0.4 -> 145.2 | H98: =D98*0.4 -> 0 | I98: =E98*0.4 -> 145.2
B99: HI-1650(पूसा ओजस्वी) APR-2024-12-763-135650-FI-B | C99: =sumif(Purchase!E$5:E1000,B99,Purchase!F$5:F1000) -> 110 | D99: =SUMIF(Sale!H:H,B99,Sale!I:I) -> 0 | E99: =C99-D99 -> 110 | F99: =VLOOKUP(B99,Table1[[Variety]:[Column1]],5,FALSE) -> 7500 | G99: =C99*0.4 -> 44 | H99: =D99*0.4 -> 0 | I99: =E99*0.4 -> 44
B100: LOK-1 BR | C100: =sumif(Purchase!E$5:E1000,B100,Purchase!F$5:F1000) -> 175 | D100: =SUMIF(Sale!H:H,B100,Sale!I:I) -> 0 | E100: =C100-D100 -> 175 | F100: =VLOOKUP(B100,Table1[[Variety]:[Column1]],5,FALSE) -> 9000 | G100: =C100*0.4 -> 70 | H100: =D100*0.4 -> 0 | I100: =E100*0.4 -> 70
B101: HI-1650(पूसा ओजस्वी) APR-2024-12-763-135650-FI-A | C101: =sumif(Purchase!E$5:E1000,B101,Purchase!F$5:F1000) -> 220 | D101: =SUMIF(Sale!H:H,B101,Sale!I:I) -> 0 | E101: =C101-D101 -> 220 | F101: =VLOOKUP(B101,Table1[[Variety]:[Column1]],5,FALSE) -> 7500 | G101: =C101*0.4 -> 88 | H101: =D101*0.4 -> 0 | I101: =E101*0.4 -> 88
...

Sheet temp
A1: Invoice no | B1: Customer name | C1: Village | D1: Mobile No | E1: item1 | F1: bag1 | G1: quantity1 | H1: rate1 | I1: amount1 | J1: item2 | K1: bag2 | L1: quantity2 | M1: rate2 | N1: amount2 | O1: item3 | P1: bag3 | Q1: quantity3 | R1: rate3 | S1: amount3 | T1: item4 | U1: bag4 | V1: quantity4 | W1: rate4 | X1: amount4 | Y1: item5 | Z1: bag5 | AA1: quantity5 | AB1: rate5 | AC1: amount5 | AD1: Date | AE1: Grand Total | AF1: packing
A2: 8846 | E2: GW-513 40KG | F2: 5 | G2: 2 | H2: 5300 | I2: 10600 | J2: HI-1655(पूसा हर्षा) 40KG | K2: 10 | L2: 4 | M2: 5300 | N2: 21200 | O2: JKG 5 KABULI 50KG | Q2: 0 | R2: 12000 | S2: 0 | V2: 0 | X2: 0 | AA2: 0 | AC2: 0 | AD2: {=Sale!V52} | AE2: =SUM(AC2, X2,S2,N2,I2) -> 31800 | AF2: 40
A3: 3597 | B3: sarang | C3: huh | D3: 21212 | E3: HI-8663 (पोषण ) APR-2024-12-763-135628-FI-B | F3: 4 | G3: 1.6 | H3: 5000 | I3: 8000 | J3: GW-513 APR-2024-12-763-135624-FII-(I)-A | K3: 3 | L3: 1.2 | M3: 5000 | N3: 6000 | Q3: 0 | S3: 0 | V3: 0 | X3: 0 | AA3: 0 | AC3: 0 | AD3: {=Sale!V52} | AE3: =SUM(AC3, X3,S3,N3,I3) -> 14000 | AF3: 40

Sheet Document Studio Logs
A1: 45919.731 | B1: Document Studio Logs | C1: 👋🏻 Please do not edit or delete this sheet)
A2: 45919.78 | B2: ✔️ Task #ouolne - Create PDF file from Sales quote | C2: {"exportFileName":"invoice","parentFolderName":"KaiZen","viewersCanCopy":true,"templateId":"1uaZo4R9aDdjSU591lPAJWjib2cPowIjAvw0Hf9DDA4g","exportMime":"application/pdf","parentFolderId":"18B9k736nxq1PXeSY7UPUBtkI0h2zg6y3","templateMime":"application/vnd.google-apps.document","sendNotifications":true,"templateName":"Sales quote"}
A3: 45919.78 | B3: ✔️ Workflow #pc5gsn - Vasundhara | C3: {"timeDelay":false,"triggerHourly":false,"sheetId":"638907871","formId":"","owner":"ninad.abhyankar88@gmail.com","triggerFormSubmit":false,"timeZone":"Asia/Calcutta","ssId":"1VFgwklCy6FlEVCuXBgnWfpL2l5rvg3gNTMn5j1RThWU","skipHidden":true} | D3: [[{"field":"{{Processed}}","value":"1","compare":"NOT_EQUAL_TO"}]]
A4: 45919.773 | B4: ✔️ Task #gzpzae - Create PDF file from Sales quote | C4: {"templateMime":"application/vnd.google-apps.document","parentFolderName":"KaiZen","templateId":"1uaZo4R9aDdjSU591lPAJWjib2cPowIjAvw0Hf9DDA4g","viewersCanCopy":true,"templateName":"Sales quote","exportFileName":"Invoice","parentFolderId":"18B9k736nxq1PXeSY7UPUBtkI0h2zg6y3","exportMime":"application/pdf","sendNotifications":true}
A5: 45919.773 | B5: ✔️ Workflow #brcrx3 - Vasundhara | C5: {"owner":"ninad.abhyankar88@gmail.com","ssId":"1VFgwklCy6FlEVCuXBgnWfpL2l5rvg3gNTMn5j1RThWU","timeZone":"Asia/Calcutta","timeDelay":false,"triggerFormSubmit":false,"sheetId":"638907871","formId":"","skipHidden":true,"triggerHourly":false} | D5: [[{"field":"{{Processed}}","value":"1","compare":"NOT_EQUAL_TO"}]]
A6: 45919.769 | B6: ✔️ Task #gzpzae - Create PDF file from Sales quote | C6: {"templateMime":"application/vnd.google-apps.document","exportFileName":"Invoice","templateName":"Sales quote","viewersCanCopy":true,"sendNotifications":true,"exportMime":"application/pdf","parentFolderId":"18B9k736nxq1PXeSY7UPUBtkI0h2zg6y3","parentFolderName":"KaiZen","templateId":"1uaZo4R9aDdjSU591lPAJWjib2cPowIjAvw0Hf9DDA4g"}
A7: 45919.769 | B7: ✔️ Workflow #brcrx3 - Vasundhara | C7: {"sheetId":"638907871","formId":"","timeDelay":false,"owner":"ninad.abhyankar88@gmail.com","triggerFormSubmit":false,"triggerHourly":false,"timeZone":"Asia/Calcutta","ssId":"1VFgwklCy6FlEVCuXBgnWfpL2l5rvg3gNTMn5j1RThWU","skipHidden":true} | D7: [[{"compare":"NOT_CONTAINS","value":"yes","field":"{{Processed}}"}]]
A8: 45919.741 | B8: ✔️ Task #gzpzae - Create PDF file from Sales quote | C8: {"parentFolderId":"18B9k736nxq1PXeSY7UPUBtkI0h2zg6y3","parentFolderName":"KaiZen","templateName":"Sales quote","templateId":"1uaZo4R9aDdjSU591lPAJWjib2cPowIjAvw0Hf9DDA4g","viewersCanCopy":true,"templateMime":"application/vnd.google-apps.document","sendNotifications":true,"exportFileName":"Invoice","exportMime":"application/pdf"}
A9: 45919.741 | B9: ✔️ Workflow #brcrx3 - Vasundhara | C9: {"formId":"","timeZone":"Asia/Calcutta","triggerFormSubmit":false,"sheetId":"638907871","triggerHourly":false,"timeDelay":false,"ssId":"1VFgwklCy6FlEVCuXBgnWfpL2l5rvg3gNTMn5j1RThWU","skipHidden":true,"owner":"ninad.abhyankar88@gmail.com"}
A10: 45919.736 | B10: ✔️ Processed 1 rows in 19 seconds | C10: 2
A11: 45919.731 | B11: ✔️ Task #gzpzae - Create PDF file from Sales quote | C11: {"exportFileName":"Invoice","templateMime":"application/vnd.google-apps.document","parentFolderName":"KaiZen","templateId":"1uaZo4R9aDdjSU591lPAJWjib2cPowIjAvw0Hf9DDA4g","templateName":"Sales quote","viewersCanCopy":true,"sendNotifications":true,"exportMime":"application/pdf","parentFolderId":"18B9k736nxq1PXeSY7UPUBtkI0h2zg6y3"}
A12: 45919.731 | B12: ✔️ Workflow #brcrx3 - Vasundhara | C12: {"timeDelay":false,"formId":"","triggerHourly":false,"skipHidden":true,"sheetId":"638907871","timeZone":"Asia/Calcutta","ssId":"1VFgwklCy6FlEVCuXBgnWfpL2l5rvg3gNTMn5j1RThWU","owner":"ninad.abhyankar88@gmail.com","triggerFormSubmit":false}
